Workbook
Name SECTOR: '[1]업체 SECTOR BACK DATA'!$A$3:$C$373

Sheet 국내
A1: RCK Order no. | B1: Customer PO | C1: NOAH O.C No. | D1: PO receipt date | E1: Period | F1: AX Project number | G1: Business registration number | H1: Customer name | I1: Opportunity | J1: Sector | K1: Industry code | L1: AX Item number | M1: Item name | N1: Currency | O1: Item qty | P1: Sales Unit Price | Q1: Sales amount | R1: ICO Unit | S1: Total ICO | T1: Incoterms | U1: 영업 담당 | V1: 공장발주 Person | W1: AX 입력 CS | X1: 공장 발주 날짜 | Y1: 공장 EXW date | Z1: Requested delivery date | AA1: 납품 주소 | AB1: Remark | AC1: 세금계산서 발행일 | AD1: Power supply | AE1: Motor(kW) | AF1: BASE | AG1: ACT Flange | AH1: Operating time | AI1: Handwheel | AJ1: RPM | AK1: Turns | AL1: Bushing | AM1: MOV | AN1: Gearbox model | AO1: Gearbox Flange | AP1: Gearbox ratio | AQ1: Gearbox position | AR1: Operating mode | AS1: Fail action | AT1: Enclosure | AU1: Cable entry | AV1: Paint | AW1: Cover tube(mm) | AX1: WD code | AY1: Test report | AZ1: Version | BA1: Remark2 | BB1: Model | BC1: Bush | BD1: ALS | BE1: EXT | BF1: DC24V | BG1: Modbus, Profibus | BH1: LCU | BI1: PIU | BJ1: CPT+PIU | BK1: PCU+PIU | BL1: -40 | BM1: -60 | BN1: SCP | BO1: EXP | BP1: Bush-SQ | BQ1: Bush-STAR | BR1: INTEGRAL | BS1: IMS | BT1: BLDC | BU1: HART, Foundation Fieldbus | BV1: ATS
A2: ND-0001 | B2: JK2026010202 | D2: 46027 | E2: P01 | F2: TBD | G2: 794-29-00426 | H2: 제이케이콘트롤 | J2: CPI | L2: 1279970 | M2: NA038 with BFV | N2: KRW | O2: 22 | P2: 875000 | Q2: =표3[[#This Row],[Item qty]]*표3[[#This Row],[Sales Unit Price]] -> 19250000 | R2: {=_xlfn.XLOOKUP($BB2&$BB2,ICO!$E:$E,ICO!$C:$C,0)+SUMPRODUCT((BC2:BV2="Y")*_xlfn.XLOOKUP($BB2&BC$1:BV$1,ICO!$E:$E,ICO!$C:$C,0))} -> 922492.84 | S2: =표3[[#This Row],[ICO Unit]]*표3[[#This Row],[Item qty]] -> 20294842 | T2: DDP | V2: 이용욱 | X2: 46030 | Z2: 46059 | AA2: TBD | AD2: 220V-1Ph-60Hz | AL2: ◇17 | AM2: Y (BFV200A) 신우밸브 사급 | AR2: 내장 PCU | AT2: IP67 | AU2: PF 3/4" | AV2: M/S | BB2: NA038 | BC2: Y | BD2: Y | BK2: Y | BP2: Y
A3: ND-0002 | B3: IAN-2601-0001 | C3: L260005 | D3: 46027 | E3: P01 | F3: TBD | G3: 814-01-00158 | H3: 이안컨트롤즈 | J3: OG | L3: 1279957 | M3: NA015 | N3: KRW | O3: 1 | P3: 812000 | Q3: =표3[[#This Row],[Item qty]]*표3[[#This Row],[Sales Unit Price]] -> 812000 | R3: {=_xlfn.XLOOKUP($BB3&$BB3,ICO!$E:$E,ICO!$C:$C,0)+SUMPRODUCT((BC3:BV3="Y")*_xlfn.XLOOKUP($BB3&BC$1:BV$1,ICO!$E:$E,ICO!$C:$C,0))} -> 787213.35 | S3: =표3[[#This Row],[ICO Unit]]*표3[[#This Row],[Item qty]] -> 787213.35 | T3: DDP | V3: 이용욱 | X3: 46030 | Y3: 46040 | Z3: 46041 | AA3: 대신화물 : 부산사상 괘법지점 신한기공 010-319-3265 | AD3: 220V-1Ph-60Hz | AL3: No 가공 | AR3: 외장 PCU | AT3: IP67 | AU3: PF 3/4" | AV3: M/S | BB3: NA015 | BC3: N | BD3: Y | BK3: Y
A4: ND-0003 | B4: DS-2511-2567_01A | D4: 46027 | E4: P01 | F4: TBD | G4: 292-87-02855 | H4: 주식회사 다윈이엔씨 | J4: CPI | M4: PCU BOARD | N4: KRW | O4: 2 | P4: 600000 | Q4: =표3[[#This Row],[Item qty]]*표3[[#This Row],[Sales Unit Price]] -> 1200000 | R4: 0 | S4: =표3[[#This Row],[ICO Unit]]*표3[[#This Row],[Item qty]] -> 0 | T4: DDP | V4: 이용욱 | W4: 김소정 | X4: 46030 | Z4: 46034 | AA4: 경남 창원시 의창구 평산로 33, 425호(팔용동, 신화더플렉스시티) | AB4: 선수금 진행 | AC4: 46030
A5: ND-0004 | B5: 202512310004 | D5: 46027 | E5: P01 | F5: TBD | G5: 113-86-05741 | H5: 케이에이아이텍(주) | J5: WAPO | L5: 1279932 | M5: SA09 | N5: KRW | O5: 1 | P5: 180000 | Q5: =표3[[#This Row],[Item qty]]*표3[[#This Row],[Sales Unit Price]] -> 180000 | R5: {=_xlfn.XLOOKUP($BB5&$BB5,ICO!$E:$E,ICO!$C:$C,0)+SUMPRODUCT((BC5:BV5="Y")*_xlfn.XLOOKUP($BB5&BC$1:BV$1,ICO!$E:$E,ICO!$C:$C,0))} -> 212993.74 | S5: =표3[[#This Row],[ICO Unit]]*표3[[#This Row],[Item qty]] -> 212993.74 | T5: DDP | V5: 이용욱 | X5: 46030 | AA5: 서울 구로구 구로동 615-3 STX W-TOWER 911호 | AD5: DC24V | AL5: Y | AR5: ON/OFF | AU5: PF 1/2" | AV5: M/S | AX5: ST-82000-A | BB5: SA009S
A6: ND-0005 | B6: NOAH 25- 2783 | D6: 46027 | E6: P01 | F6: TBD | G6: 311-81-51048 | H6: ㈜ 명신일렉트릭 | L6: 1279965 | M6: NA028 | N6: KRW | O6: 1 | P6: 1440000 | Q6: =표3[[#This Row],[Item qty]]*표3[[#This Row],[Sales Unit Price]] -> 1440000 | R6: {=_xlfn.XLOOKUP($BB6&$BB6,ICO!$E:$E,ICO!$C:$C,0)+SUMPRODUCT((BC6:BV6="Y")*_xlfn.XLOOKUP($BB6&BC$1:BV$1,ICO!$E:$E,ICO!$C:$C,0))} -> 512336.3 | S6: =표3[[#This Row],[ICO Unit]]*표3[[#This Row],[Item qty]] -> 512336.3 | T6: DDP | V6: 이용욱 | W6: 방정택 | X6: 46030 | AA6: 충청남도 당진시 송산면 유두골길 101 | AB6: 선수금 진행 | AD6: 220V-1Ph-60Hz | AL6: No 가공 | AR6: ON/OFF | AT6: IP67 | AU6: PF 3/4" | AV6: M/S | AX6: NS-12000-C | BB6: NA028 | BC6: N | BD6: Y
A7: ND-0006 | B7: VT-C35-251218-01 | D7: 46027 | E7: P01 | F7: TBD | G7: 775-88-01381 | H7: 주식회사 브이티엘 | J7: CPI | M7: MA003/SBWG-07-1SM | N7: KRW | O7: 4 | P7: 7250000 | Q7: =표3[[#This Row],[Item qty]]*표3[[#This Row],[Sales Unit Price]] -> 29000000 | R7: {=_xlfn.XLOOKUP($BB7&$BB7,ICO!$E:$E,ICO!$C:$C,0)+SUMPRODUCT((BC7:BV7="Y")*_xlfn.XLOOKUP($BB7&BC$1:BV$1,ICO!$E:$E,ICO!$C:$C,0))} -> 0 | S7: =표3[[#This Row],[ICO Unit]]*표3[[#This Row],[Item qty]] -> 0 | T7: DDP | V7: 이용욱 | X7: 46031 | AA7: 경남 창원시 진해구 남양동 404 ㈜브이티엘 | AD7: 415V-3Ph-50Hz | AE7: 3.7 | AJ7: 82.5 | AN7: SBWG-07-1SM | AO7: F40 / RF | AP7: 272:1 | AR7: INT_ON/OFF | AT7: IP68 | AU7: M40 - 1ea / MA25 - 2ea | AV7: Color : RAL 9002 1st(40 mic) : EP170PTA-2263 2nd(40 mic) : UT2578(S)-I-SHS2002-Y (0004D) | AX7: MX-3A1-A | BA7: Sunshade 적용 Handle 방향 확인 | BB7: MA03 | BR7: Y
A8: ND-0007 | B8: GE-05 | D8: 46027 | E8: P01 | F8: TBD | G8: 113-15-83752 | H8: 굿이엔지 | J8: OG | M8: MS02 | N8: KRW | O8: 3 | P8: 1350000 | Q8: =표3[[#This Row],[Item qty]]*표3[[#This Row],[Sales Unit Price]] -> 4050000 | R8: {=_xlfn.XLOOKUP($BB8&$BB8,ICO!$E:$E,ICO!$C:$C,0)+SUMPRODUCT((BC8:BV8="Y")*_xlfn.XLOOKUP($BB8&BC$1:BV$1,ICO!$E:$E,ICO!$C:$C,0))} -> 0 | S8: =표3[[#This Row],[ICO Unit]]*표3[[#This Row],[Item qty]] -> 0 | T8: DDP | V8: 이용욱 | X8: 46031 | AD8: 380V_3PH_60Hz | AE8: 1.5 | AF8: Non thrust | AJ8: 36.6 | AR8: ON/OFF | BB8: MS02
A9: ND-0008 | B9: 202601050001 | D9: 46027 | E9: P01 | F9: TBD | G9: 113-86-05741 | H9: 케이에이아이텍(주) | J9: CPI | L9: 1279932 | M9: SA09 | N9: KRW | O9: 10 | P9: 180000 | Q9: =표3[[#This Row],[Item qty]]*표3[[#This Row],[Sales Unit Price]] -> 1800000 | R9: {=_xlfn.XLOOKUP($BB9&$BB9,ICO!$E:$E,ICO!$C:$C,0)+SUMPRODUCT((BC9:BV9="Y")*_xlfn.XLOOKUP($BB9&BC$1:BV$1,ICO!$E:$E,ICO!$C:$C,0))} -> 212993.74 | S9: =표3[[#This Row],[ICO Unit]]*표3[[#This Row],[Item qty]] -> 2129937.4 | T9: DDP | V9: 이용욱 | X9: 46031 | AA9: 서울 구로구 구로동 615-3 STX W-TOWER 911호 | AD9: 220V-1Ph-60Hz | AL9: No 가공 | AR9: ON/OFF | AU9: PF 1/2" | AX9: ST-12000-A | BB9: SA009S
A10: ND-0009 | B10: TP-260105-01 | D10: 46028 | E10: P01 | F10: TBD | G10: 606-81-95134 | H10: (주)티엠아이 | J10: CPI | M10: PCU BOARD | N10: KRW | O10: 1 | P10: 330000 | Q10: =표3[[#This Row],[Item qty]]*표3[[#This Row],[Sales Unit Price]] -> 330000 | R10: {=_xlfn.XLOOKUP($BB10&$BB10,ICO!$E:$E,ICO!$C:$C,0)+SUMPRODUCT((BC10:BV10="Y")*_xlfn.XLOOKUP($BB10&BC$1:BV$1,ICO!$E:$E,ICO!$C:$C,0))} -> 0 | S10: =표3[[#This Row],[ICO Unit]]*표3[[#This Row],[Item qty]] -> 0 | T10: DDP | V10: 이용욱 | X10: 46031 | Z10: 46030 | AA10: 경남 김해시 김해대로 2419 2층 티엠아이 / 노병철 이사 010-2866-4509 | AB10: TP-260105-01
A11: ND-0010 | B11: JK2026010601 | D11: 46028 | E11: P01 | F11: TBD | G11: 794-29-00426 | H11: 제이케이콘트롤 | J11: CPI | L11: 1279970 | M11: NA038_INT ON/OFF_방폭 | N11: KRW | O11: 1 | P11: 1288000 | Q11: =표3[[#This Row],[Item qty]]*표3[[#This Row],[Sales Unit Price]] -> 1288000 | R11: {=_xlfn.XLOOKUP($BB11&$BB11,ICO!$E:$E,ICO!$C:$C,0)+SUMPRODUCT((BC11:BV11="Y")*_xlfn.XLOOKUP($BB11&BC$1:BV$1,ICO!$E:$E,ICO!$C:$C,0))} -> 1353373.7 | S11: =표3[[#This Row],[ICO Unit]]*표3[[#This Row],[Item qty]] -> 1353373.7 | T11: DDP | V11: 이용욱 | X11: 46031 | Z11: 46050 | AA11: 서울시 금천구 시흥대로 97 시흥산업용재유통센터 19동 120호 제이케이콘트롤 / 이재강대표 010-2081-0180 | AD11: 220V-1Ph-60Hz | AR11: INT_ON/OFF | AT11: EX d llB T4 | AU11: NPT 1" - 1ea / NPT 3/4" - 2ea | AV11: M/S | AX11: NS-201-B | BB11: NA038 | BO11: Y | BR11: Y
A12: ND-0011 | B12: NM-25104108 | D12: 46029 | E12: P01 | F12: TBD | G12: 606-38-53837 | H12: 노아마린(NOAH MARINE) | J12: CPI | L12: 1279961 | M12: NA019 | N12: KRW | O12: 3 | P12: 1840000 | Q12: =표3[[#This Row],[Item qty]]*표3[[#This Row],[Sales Unit Price]] -> 5520000 | R12: {=_xlfn.XLOOKUP($BB12&$BB12,ICO!$E:$E,ICO!$C:$C,0)+SUMPRODUCT((BC12:BV12="Y")*_xlfn.XLOOKUP($BB12&BC$1:BV$1,ICO!$E:$E,ICO!$C:$C,0))} -> 0 | S12: =표3[[#This Row],[ICO Unit]]*표3[[#This Row],[Item qty]] -> 0 | T12: DDP | V12: 이용욱 | Z12: 46058
A13: NDE-0012 | B13: INCO-260107-002 | C13: N/A | D13: 46029 | E13: P01 | F13: TBD | G13: 238-87-02400 | H13: 주식회사 아이엔씨코리아(I&C KOREA Inc.) | J13: CPI | M13: 수동 핸들 | N13: KRW | O13: 3 | P13: 50000 | Q13: =표3[[#This Row],[Item qty]]*표3[[#This Row],[Sales Unit Price]] -> 150000 | R13: {=_xlfn.XLOOKUP($BB13&$BB13,ICO!$E:$E,ICO!$C:$C,0)+SUMPRODUCT((BC13:BV13="Y")*_xlfn.XLOOKUP($BB13&BC$1:BV$1,ICO!$E:$E,ICO!$C:$C,0))} -> 0 | S13: =표3[[#This Row],[ICO Unit]]*표3[[#This Row],[Item qty]] -> 0 | T13: DDP | V13: 이용욱 | X13: 46029 | Y13: 46029 | AB13: 긴급 발주 건
A14: ND-0013 | B14: N/A | D14: 46029 | E14: P01 | F14: TBD | G14: 117-81-76942 | H14: 오토밸브엔지니어링 | J14: OG | L14: 1280032 | M14: SA005L | N14: KRW | O14: 3 | P14: 530000 | Q14: =표3[[#This Row],[Item qty]]*표3[[#This Row],[Sales Unit Price]] -> 1590000 | R14: {=_xlfn.XLOOKUP($BB14&$BB14,ICO!$E:$E,ICO!$C:$C,0)+SUMPRODUCT((BC14:BV14="Y")*_xlfn.XLOOKUP($BB14&BC$1:BV$1,ICO!$E:$E,ICO!$C:$C,0))} -> 0 | S14: =표3[[#This Row],[ICO Unit]]*표3[[#This Row],[Item qty]] -> 0 | T14: DDP | V14: 이용욱 | Z14: 46029 | AA14: 대신화물-대전대화동, 경성유체기술 최동규 부장님 010-4190-3365
A15: ND-0014 | B15: IAN-2601-0002 | D15: 46029 | E15: P01 | F15: TBD | G15: 814-01-00158 | H15: 이안컨트롤즈 | J15: OG | M15: 3WAY L타입 | N15: KRW | O15: 2 | P15: 85600 | Q15: =표3[[#This Row],[Item qty]]*표3[[#This Row],[Sales Unit Price]] -> 171200 | R15: {=_xlfn.XLOOKUP($BB15&$BB15,ICO!$E:$E,ICO!$C:$C,0)+SUMPRODUCT((BC15:BV15="Y")*_xlfn.XLOOKUP($BB15&BC$1:BV$1,ICO!$E:$E,ICO!$C:$C,0))} -> 0 | S15: =표3[[#This Row],[ICO Unit]]*표3[[#This Row],[Item qty]] -> 0 | T15: DDP | V15: 이용욱 | Z15: 46030
A16: ND-0015 | B16: N/A | D16: 46030 | E16: P01 | F16: TBD | G16: 121-08-40402 | H16: 오성에어테크 | J16: CPI | L16: 1279931 | M16: SA-05X | N16: KRW | O16: 31 | P16: 0 | Q16: =표3[[#This Row],[Item qty]]*표3[[#This Row],[Sales Unit Price]] -> 0 | R16: {=_xlfn.XLOOKUP($BB16&$BB16,ICO!$E:$E,ICO!$C:$C,0)+SUMPRODUCT((BC16:BV16="Y")*_xlfn.XLOOKUP($BB16&BC$1:BV$1,ICO!$E:$E,ICO!$C:$C,0))} -> 0 | S16: =표3[[#This Row],[ICO Unit]]*표3[[#This Row],[Item qty]] -> 0 | T16: DDP | V16: 이용욱 | AA16: 노아엑츄에이션 본사 방문출고
A17: ND-0016 | B17: PO-4-26-0108-0006 Rev.0 | D17: 46030 | E17: P01 | F17: TBD | G17: 312-81-03840 | H17: (주)삼신 | J17: WAPO | M17: Spare | N17: KRW | O17: 25 | P17: 375000 | Q17: =표3[[#This Row],[Item qty]]*표3[[#This Row],[Sales Unit Price]] -> 9375000 | R17: {=_xlfn.XLOOKUP($BB17&$BB17,ICO!$E:$E,ICO!$C:$C,0)+SUMPRODUCT((BC17:BV17="Y")*_xlfn.XLOOKUP($BB17&BC$1:BV$1,ICO!$E:$E,ICO!$C:$C,0))} -> 0 | S17: =표3[[#This Row],[ICO Unit]]*표3[[#This Row],[Item qty]] -> 0 | T17: DDP | V17: 이용욱 | X17: 46031 | AA17: 충남 천안시 서북구 입장면 성진로 1138-11호 (주)삼신 / 박성해 대리 010 8622 5414
A18: ND-0017 | B18: KR26-SA01 FOC 대정밸브 샘플 | D18: 46030 | E18: P01 | F18: 82-15533.001 | G18: 503-81-25251 | H18: 대정밸브 | J18: CPI | L18: 1279949 | M18: Noah NA006 WT | N18: KRW | O18: 1 | P18: 0 | Q18: 0 | R18: 184211 | S18: =표3[[#This Row],[ICO Unit]]*표3[[#This Row],[Item qty]] -> 184211 | T18: DDP | V18: 이용욱 | W18: 이상권 | X18: 46031 | Y18: 46031 | Z18: 46045 | AA18: 대신화물 대구 달서 호산 대정밸브 이 성 국 차장님 053-584-2278 | AB18: 긴급 발주 건 (김한솔) | AD18: 220V-1Ph-60Hz | AL18: ㅁ17 | AR18: ON/OFF | AT18: IP67 | AX18: NS-12000-C | BC18: Y | BP18: Y
A19: ND-0018 | B19: N/A | D19: 46031 | E19: P01 | F19: TBD | G19: 117-81-76942 | H19: 오토밸브 | J19: OG | M19: SA05X-DA | N19: KRW | O19: 2 | R19: {=_xlfn.XLOOKUP($BB19&$BB19,ICO!$E:$E,ICO!$C:$C,0)+SUMPRODUCT((BC19:BV19="Y")*_xlfn.XLOOKUP($BB19&BC$1:BV$1,ICO!$E:$E,ICO!$C:$C,0))} -> 0 | S19: =표3[[#This Row],[ICO Unit]]*표3[[#This Row],[Item qty]] -> 0 | T19: DDP | AA19: 서울특별시 구로구 경인로53가길 10,1112 호(구로동,구로대명벨리온 지식산업센터) | AD19: AC220V | AR19: ON/OFF
B20: 202601090004 | D20: 46031 | E20: P01 | F20: TBD | H20: 케이에이아이텍(주) | J20: CPI | M20: SA09X-PCU(4-25mA)-220V | N20: KRW | O20: 4 | P20: 620000 | Q20: =표3[[#This Row],[Item qty]]*표3[[#This Row],[Sales Unit Price]] -> 2480000 | R20: {=_xlfn.XLOOKUP($BB20&$BB20,ICO!$E:$E,ICO!$C:$C,0)+SUMPRODUCT((BC20:BV20="Y")*_xlfn.XLOOKUP($BB20&BC$1:BV$1,ICO!$E:$E,ICO!$C:$C,0))} -> 0 | S20: =표3[[#This Row],[ICO Unit]]*표3[[#This Row],[Item qty]] -> 0 | T20: DDP | AT20: Ex d IIB T6

Sheet 해외
A1: RCK Order no. | B1: Customer PO | C1: NOAH O.C No. | D1: PO receipt date | E1: Period | F1: AX Project number | G1: Business registration number | H1: Customer name | I1: Opportunity | J1: Sector | K1: Industry code | L1: AX Item number | M1: Item name | N1: Currency | O1: Item qty | P1: Sales Unit Price | Q1: Sales amount | R1: ICO Unit | S1: Total ICO | T1: Incoterms | U1: 영업 담당 | V1: 공장발주 Person | W1: AX 입력 CS | X1: 공장 발주 날짜 | Y1: 공장 EXW date | Z1: Requested delivery date | AA1: 납품 주소 | AB1: Remark | AC1: 세금계산서 발행일 | AD1: Power supply | AE1: Motor(kW) | AF1: ACT Flange | AG1: Operating time | AH1: Handwheel | AI1: RPM | AJ1: Turns | AK1: Bushing | AL1: MOV | AM1: Gearbox model | AN1: Gearbox Flange | AO1: Gearbox ratio | AP1: Gearbox position | AQ1: Operating mode | AR1: Fail action | AS1: Enclosure | AT1: Cable entry | AU1: Paint | AV1: Cover tube(mm) | AW1: WD code | AX1: Test report | AY1: Version | AZ1: Model | BA1: Bush | BB1: ALS | BC1: EXT | BD1: DC24V | BE1: Modbus, Profibus | BF1: LCU | BG1: PIU | BH1: CPT+PIU | BI1: PCU+PIU | BJ1: -40 | BK1: -60 | BL1: SCP | BM1: EXP | BN1: Bush-SQ | BO1: Bush-STAR | BP1: INTEGRAL | BQ1: IMS | BR1: BLDC | BS1: HART, Foundation Fieldbus | BT1: ATS
A2: NO-0001 | B2: 4000446107 | D2: 46027 | E2: P01 | F2: TBD | G2: C-0054 | H2: MRC Global(New Zealand) Ltd. | J2: =_xlfn.XLOOKUP(표3_3[[#This Row],[Business registration number]],'Customer master_해외'!A:A,'Customer master_해외'!J:J) -> CPI | L2: =_xlfn.XLOOKUP(표3_3[[#This Row],[Model]],'Item-mapping'!J:J,'Item-mapping'!A:A) -> 1279930 | M2: SA005L | N2: USD | O2: 1 | P2: 504 | Q2: =표3_3[[#This Row],[Item qty]]*표3_3[[#This Row],[Sales Unit Price]] -> 504 | R2: {=_xlfn.XLOOKUP($AZ2&$AZ2,ICO!$E:$E,ICO!$C:$C,0)+SUMPRODUCT((BA2:BT2="Y")*_xlfn.XLOOKUP($AZ2&BA$1:BT$1,ICO!$E:$E,ICO!$C:$C,0))} -> 513775.44 | S2: =표3_3[[#This Row],[ICO Unit]]*표3_3[[#This Row],[Item qty]] -> 513775.44 | T2: FOB | V2: 방정택 | X2: 46031 | AD2: 24DC | AZ2: SA005L | BC2: Y | BI2: Y
A3: NO-0002 | B3: 068112-00 | D3: 46028 | E3: P01 | F3: TBD | G3: C-0034 | H3: FLOMATIC CORPORATION | J3: =_xlfn.XLOOKUP(표3_3[[#This Row],[Business registration number]],'Customer master_해외'!A:A,'Customer master_해외'!J:J) -> WAPO | L3: =_xlfn.XLOOKUP(표3_3[[#This Row],[Model]],'Item-mapping'!J:J,'Item-mapping'!A:A) -> 1279957 | M3: FCEL-15ALS | N3: USD | O3: 8 | P3: 430 | Q3: =표3_3[[#This Row],[Item qty]]*표3_3[[#This Row],[Sales Unit Price]] -> 3440 | R3: {=_xlfn.XLOOKUP($AZ3&$AZ3,ICO!$E:$E,ICO!$C:$C,0)+SUMPRODUCT((BA3:BT3="Y")*_xlfn.XLOOKUP($AZ3&BA$1:BT$1,ICO!$E:$E,ICO!$C:$C,0))} -> 456209.57 | S3: =표3_3[[#This Row],[ICO Unit]]*표3_3[[#This Row],[Item qty]] -> 3649676.5 | T3: FOB | V3: 방정택 | X3: 46031 | AD3: 120VAC | AZ3: NA015 | BB3: Y
A4: NO-0002 | B4: 068112-00 | D4: 46028 | E4: P01 | F4: TBD | G4: C-0034 | H4: FLOMATIC CORPORATION | J4: =_xlfn.XLOOKUP(표3_3[[#This Row],[Business registration number]],'Customer master_해외'!A:A,'Customer master_해외'!J:J) -> WAPO | L4: =_xlfn.XLOOKUP(표3_3[[#This Row],[Model]],'Item-mapping'!J:J,'Item-mapping'!A:A) -> 1279965 | M4: FCEL-28ALS | N4: USD | O4: 8 | P4: 483 | Q4: =표3_3[[#This Row],[Item qty]]*표3_3[[#This Row],[Sales Unit Price]] -> 3864 | R4: {=_xlfn.XLOOKUP($AZ4&$AZ4,ICO!$E:$E,ICO!$C:$C,0)+SUMPRODUCT((BA4:BT4="Y")*_xlfn.XLOOKUP($AZ4&BA$1:BT$1,ICO!$E:$E,ICO!$C:$C,0))} -> 512336.3 | S4: =표3_3[[#This Row],[ICO Unit]]*표3_3[[#This Row],[Item qty]] -> 4098690.4 | T4: FOB | V4: 방정택 | X4: 46031 | AD4: 120VAC | AZ4: NA028 | BB4: Y
A5: NO-0002 | B5: 068112-00 | D5: 46028 | E5: P01 | F5: TBD | G5: C-0034 | H5: FLOMATIC CORPORATION | J5: =_xlfn.XLOOKUP(표3_3[[#This Row],[Business registration number]],'Customer master_해외'!A:A,'Customer master_해외'!J:J) -> WAPO | L5: =_xlfn.XLOOKUP(표3_3[[#This Row],[Model]],'Item-mapping'!J:J,'Item-mapping'!A:A) -> 1279977 | M5: FCEL-60ALS | N5: USD | O5: 3 | P5: 648 | Q5: =표3_3[[#This Row],[Item qty]]*표3_3[[#This Row],[Sales Unit Price]] -> 1944 | R5: {=_xlfn.XLOOKUP($AZ5&$AZ5,ICO!$E:$E,ICO!$C:$C,0)+SUMPRODUCT((BA5:BT5="Y")*_xlfn.XLOOKUP($AZ5&BA$1:BT$1,ICO!$E:$E,ICO!$C:$C,0))} -> 690790.51 | S5: =표3_3[[#This Row],[ICO Unit]]*표3_3[[#This Row],[Item qty]] -> 2072371.5 | T5: FOB | V5: 방정택 | X5: 46031 | AD5: 120VAC | AZ5: NA060 | BB5: Y
A6: NO-0002 | B6: 068112-00 | D6: 46028 | E6: P01 | F6: TBD | G6: C-0034 | H6: FLOMATIC CORPORATION | J6: =_xlfn.XLOOKUP(표3_3[[#This Row],[Business registration number]],'Customer master_해외'!A:A,'Customer master_해외'!J:J) -> WAPO | L6: =_xlfn.XLOOKUP(표3_3[[#This Row],[Model]],'Item-mapping'!J:J,'Item-mapping'!A:A) -> 1279953 | M6: FCEL-9ALS | N6: USD | O6: 2 | P6: 347 | Q6: =표3_3[[#This Row],[Item qty]]*표3_3[[#This Row],[Sales Unit Price]] -> 694 | R6: {=_xlfn.XLOOKUP($AZ6&$AZ6,ICO!$E:$E,ICO!$C:$C,0)+SUMPRODUCT((BA6:BT6="Y")*_xlfn.XLOOKUP($AZ6&BA$1:BT$1,ICO!$E:$E,ICO!$C:$C,0))} -> 369860.75 | S6: =표3_3[[#This Row],[ICO Unit]]*표3_3[[#This Row],[Item qty]] -> 739721.51 | T6: FOB | V6: 방정택 | X6: 46031 | AD6: 120VAC | AZ6: NA009 | BB6: Y
A7: NO-0003 | B7: 068118-00 | D7: 46030 | E7: P01 | F7: TBD | G7: C-0034 | H7: FLOMATIC CORPORATION | J7: =_xlfn.XLOOKUP(표3_3[[#This Row],[Business registration number]],'Customer master_해외'!A:A,'Customer master_해외'!J:J) -> WAPO | L7: =_xlfn.XLOOKUP(표3_3[[#This Row],[Model]],'Item-mapping'!J:J,'Item-mapping'!A:A) -> 1279985 | M7: FCEL-100ALS | N7: USD | O7: 2 | P7: 734 | Q7: =표3_3[[#This Row],[Item qty]]*표3_3[[#This Row],[Sales Unit Price]] -> 1468 | R7: {=_xlfn.XLOOKUP($AZ7&$AZ7,ICO!$E:$E,ICO!$C:$C,0)+SUMPRODUCT((BA7:BT7="Y")*_xlfn.XLOOKUP($AZ7&BA$1:BT$1,ICO!$E:$E,ICO!$C:$C,0))} -> 801604.82 | S7: =표3_3[[#This Row],[ICO Unit]]*표3_3[[#This Row],[Item qty]] -> 1603209.6 | T7: FOB | V7: 방정택 | X7: 46031 | AD7: 120VAC | AZ7: NA100 | BB7: Y
A8: NO-0003 | B8: 068118-00 | D8: 46030 | E8: P01 | F8: TBD | G8: C-0034 | H8: FLOMATIC CORPORATION | J8: =_xlfn.XLOOKUP(표3_3[[#This Row],[Business registration number]],'Customer master_해외'!A:A,'Customer master_해외'!J:J) -> WAPO | L8: =_xlfn.XLOOKUP(표3_3[[#This Row],[Model]],'Item-mapping'!J:J,'Item-mapping'!A:A) -> 1279965 | M8: FCEL-28ALS | N8: USD | O8: 5 | P8: 483 | Q8: =표3_3[[#This Row],[Item qty]]*표3_3[[#This Row],[Sales Unit Price]] -> 2415 | R8: {=_xlfn.XLOOKUP($AZ8&$AZ8,ICO!$E:$E,ICO!$C:$C,0)+SUMPRODUCT((BA8:BT8="Y")*_xlfn.XLOOKUP($AZ8&BA$1:BT$1,ICO!$E:$E,ICO!$C:$C,0))} -> 512336.3 | S8: =표3_3[[#This Row],[ICO Unit]]*표3_3[[#This Row],[Item qty]] -> 2561681.5 | T8: FOB | V8: 방정택 | X8: 46031 | AD8: 120VAC | AZ8: NA028 | BB8: Y
A9: NO-0003 | B9: 068118-00 | D9: 46030 | E9: P01 | F9: TBD | G9: C-0034 | H9: FLOMATIC CORPORATION | J9: =_xlfn.XLOOKUP(표3_3[[#This Row],[Business registration number]],'Customer master_해외'!A:A,'Customer master_해외'!J:J) -> WAPO | L9: =_xlfn.XLOOKUP(표3_3[[#This Row],[Model]],'Item-mapping'!J:J,'Item-mapping'!A:A) -> 1279973 | M9: FCEL-50ALS | N9: USD | O9: 16 | P9: 603 | Q9: =표3_3[[#This Row],[Item qty]]*표3_3[[#This Row],[Sales Unit Price]] -> 9648 | R9: {=_xlfn.XLOOKUP($AZ9&$AZ9,ICO!$E:$E,ICO!$C:$C,0)+SUMPRODUCT((BA9:BT9="Y")*_xlfn.XLOOKUP($AZ9&BA$1:BT$1,ICO!$E:$E,ICO!$C:$C,0))} -> 654811.84 | S9: =표3_3[[#This Row],[ICO Unit]]*표3_3[[#This Row],[Item qty]] -> 10476989 | T9: FOB | V9: 방정택 | X9: 46031 | AD9: 120VAC | AZ9: NA050 | BB9: Y
A10: NO-0004 | B10: 2040538 | D10: 46030 | E10: P01 | F10: TBD | G10: C-0001 | H10: ASC ENGINEERED SOLUTIONS | J10: =_xlfn.XLOOKUP(표3_3[[#This Row],[Business registration number]],'Customer master_해외'!A:A,'Customer master_해외'!J:J) -> CPI | L10: =_xlfn.XLOOKUP(표3_3[[#This Row],[Model]],'Item-mapping'!J:J,'Item-mapping'!A:A) -> 1279957 | M10: ACTE E-015B-A1A-A1, 120VAC,WITH AUX LIMIT SWITCHES | N10: USD | O10: 100 | P10: 384 | Q10: =표3_3[[#This Row],[Item qty]]*표3_3[[#This Row],[Sales Unit Price]] -> 38400 | R10: {=_xlfn.XLOOKUP($AZ10&$AZ10,ICO!$E:$E,ICO!$C:$C,0)+SUMPRODUCT((BA10:BT10="Y")*_xlfn.XLOOKUP($AZ10&BA$1:BT$1,ICO!$E:$E,ICO!$C:$C,0))} -> 456209.57 | S10: =표3_3[[#This Row],[ICO Unit]]*표3_3[[#This Row],[Item qty]] -> 45620957 | T10: FOB | V10: 방정택 | X10: 46031 | AD10: 120VAC | AZ10: NA015 | BB10: Y
A11: NO-0004 | B11: 2040538 | D11: 46030 | E11: P01 | F11: TBD | G11: C-0001 | H11: ASC ENGINEERED SOLUTIONS | J11: =_xlfn.XLOOKUP(표3_3[[#This Row],[Business registration number]],'Customer master_해외'!A:A,'Customer master_해외'!J:J) -> CPI | L11: =_xlfn.XLOOKUP(표3_3[[#This Row],[Model]],'Item-mapping'!J:J,'Item-mapping'!A:A) -> 1280044 | M11: ACTE E-SR2600-D1A-A1CW, 24VDC, AUX LIMIT SWITCHES, FAIL-CW | N11: USD | O11: 39 | P11: 2959.72 | Q11: =표3_3[[#This Row],[Item qty]]*표3_3[[#This Row],[Sales Unit Price]] -> 115429.08 | R11: {=_xlfn.XLOOKUP($AZ11&$AZ11,ICO!$E:$E,ICO!$C:$C,0)+SUMPRODUCT((BA11:BT11="Y")*_xlfn.XLOOKUP($AZ11&BA$1:BT$1,ICO!$E:$E,ICO!$C:$C,0))} -> 4560656.5 | S11: =표3_3[[#This Row],[ICO Unit]]*표3_3[[#This Row],[Item qty]] -> 1.778656e+08 | T11: FOB | V11: 방정택 | X11: 46031 | AD11: 120VAC | AR11: Fail Close | AZ11: SR30 | BB11: Y | BD11: Y
A12: NO-0005 | B12: 068087-00 | D12: 46020 | E12: P01 | F12: TBD | G12: C-0034 | H12: FLOMATIC CORPORATION | J12: =_xlfn.XLOOKUP(표3_3[[#This Row],[Business registration number]],'Customer master_해외'!A:A,'Customer master_해외'!J:J) -> WAPO | L12: =_xlfn.XLOOKUP(표3_3[[#This Row],[Model]],'Item-mapping'!J:J,'Item-mapping'!A:A) -> 1279953 | M12: FCEL-9ALS | N12: USD | O12: 4 | P12: 347 | Q12: =표3_3[[#This Row],[Item qty]]*표3_3[[#This Row],[Sales Unit Price]] -> 1388 | R12: {=_xlfn.XLOOKUP($AZ12&$AZ12,ICO!$E:$E,ICO!$C:$C,0)+SUMPRODUCT((BA12:BT12="Y")*_xlfn.XLOOKUP($AZ12&BA$1:BT$1,ICO!$E:$E,ICO!$C:$C,0))} -> 369860.75 | S12: =표3_3[[#This Row],[ICO Unit]]*표3_3[[#This Row],[Item qty]] -> 1479443 | T12: FOB | V12: 방정택 | X12: 46031 | AD12: 120VAC | AZ12: NA009 | BB12: Y

Sheet Item detail
A1: Item number | B1: Item name | C1: Search name | D1: Item group | E1: Main group | F1: Item type | G1: Global item type | H1: Status | I1: Feature group | J1: Key
A2: 1279949 | B2: Noah NA006 WT | C2: NOAH/NA006 | D2: Noah-NA | E2: ELActuator | F2: Item | G2: Rotork Price List Items | I2: Noah-NA | J2: =MID(B2,6,5) -> NA006
A3: 1279950 | B3: Noah NA006 EXP | C3: NOAH/NA006X | D3: Noah-NA | E3: ELActuator | F3: Item | G3: Rotork Price List Items | I3: Noah-NA | J3: =MID(B3,6,5) -> NA006
A4: 1279951 | B4: Noah NA006 -40 | C4: NOAH/NA006CW1 | D4: Noah-NA | E4: ELActuator | F4: Item | G4: Rotork Price List Items | I4: Noah-NA | J4: =MID(B4,6,5) -> NA006
A5: 1279952 | B5: Noah NA006 -60 | C5: NOAH/NA006CW2 | D5: Noah-NA | E5: ELActuator | F5: Item | G5: Rotork Price List Items | I5: Noah-NA | J5: =MID(B5,6,5) -> NA006
A6: 1279953 | B6: Noah NA009 WT | C6: NOAH/NA009 | D6: Noah-NA | E6: ELActuator | F6: Item | G6: Rotork Price List Items | I6: Noah-NA | J6: =MID(B6,6,5) -> NA009
A7: 1279954 | B7: Noah NA009 EXP | C7: NOAH/NA009X | D7: Noah-NA | E7: ELActuator | F7: Item | G7: Rotork Price List Items | I7: Noah-NA | J7: =MID(B7,6,5) -> NA009
A8: 1279955 | B8: Noah NA009 -40 | C8: NOAH/NA009CW1 | D8: Noah-NA | E8: ELActuator | F8: Item | G8: Rotork Price List Items | I8: Noah-NA | J8: =MID(B8,6,5) -> NA009
A9: 1279956 | B9: Noah NA009 -60 | C9: NOAH/NA009CW2 | D9: Noah-NA | E9: ELActuator | F9: Item | G9: Rotork Price List Items | I9: Noah-NA | J9: =MID(B9,6,5) -> NA009
A10: 1279957 | B10: Noah NA015 WT | C10: NOAH/NA015 | D10: Noah-NA | E10: ELActuator | F10: Item | G10: Rotork Price List Items | I10: Noah-NA | J10: =MID(B10,6,5) -> NA015
A11: 1279958 | B11: Noah NA015 EXP | C11: NOAH/NA015X | D11: Noah-NA | E11: ELActuator | F11: Item | G11: Rotork Price List Items | I11: Noah-NA | J11: =MID(B11,6,5) -> NA015
A12: 1279959 | B12: Noah NA015 -40 | C12: NOAH/NA015CW1 | D12: Noah-NA | E12: ELActuator | F12: Item | G12: Rotork Price List Items | I12: Noah-NA | J12: =MID(B12,6,5) -> NA015
A13: 1279960 | B13: Noah NA015 -60 | C13: NOAH/NA015CW2 | D13: Noah-NA | E13: ELActuator | F13: Item | G13: Rotork Price List Items | I13: Noah-NA | J13: =MID(B13,6,5) -> NA015
... A190: Noah-SR | B190: Noah-SR | C190: Noah-SR | D190: Noah-SR | E190: ELActuator | F190: BOM | G190: BOM Template Items | I190: Noah-SR | J190: =MID(B190,6,5) -> SR
B191: MA03 | J191: =MID(B191,6,5)

Sheet Item-mapping
A1: Item number | B1: Item name | C1: Search name | D1: Item group | E1: Main group | F1: Item type | G1: Global item type | H1: Status | I1: Feature group | J1: Key
A2: 1279949 | B2: Noah NA006 WT | C2: NOAH/NA006 | D2: Noah-NA | E2: ELActuator | F2: Item | G2: Rotork Price List Items | I2: Noah-NA | J2: NA006
A3: 1279953 | B3: Noah NA009 WT | C3: NOAH/NA009 | D3: Noah-NA | E3: ELActuator | F3: Item | G3: Rotork Price List Items | I3: Noah-NA | J3: NA009
A4: 1279957 | B4: Noah NA015 WT | C4: NOAH/NA015 | D4: Noah-NA | E4: ELActuator | F4: Item | G4: Rotork Price List Items | I4: Noah-NA | J4: NA015
A5: 1279961 | B5: Noah NA019 WT | C5: NOAH/NA019 | D5: Noah-NA | E5: ELActuator | F5: Item | G5: Rotork Price List Items | I5: Noah-NA | J5: NA019
A6: 1279965 | B6: Noah NA028 WT | C6: NOAH/NA028 | D6: Noah-NA | E6: ELActuator | F6: Item | G6: Rotork Price List Items | I6: Noah-NA | J6: NA028
A7: 1279969 | B7: Noah NA038 WT | C7: NOAH/NA038 | D7: Noah-NA | E7: ELActuator | F7: Item | G7: Rotork Price List Items | I7: Noah-NA | J7: NA038
A8: 1279973 | B8: Noah NA050 WT | C8: NOAH/NA050 | D8: Noah-NA | E8: ELActuator | F8: Item | G8: Rotork Price List Items | I8: Noah-NA | J8: NA050
A9: 1279977 | B9: Noah NA060 WT | C9: NOAH/NA060 | D9: Noah-NA | E9: ELActuator | F9: Item | G9: Rotork Price List Items | I9: Noah-NA | J9: NA060
A10: 1279981 | B10: Noah NA080 WT | C10: NOAH/NA080 | D10: Noah-NA | E10: ELActuator | F10: Item | G10: Rotork Price List Items | I10: Noah-NA | J10: NA080
A11: 1279985 | B11: Noah NA100 WT | C11: NOAH/NA100 | D11: Noah-NA | E11: ELActuator | F11: Item | G11: Rotork Price List Items | I11: Noah-NA | J11: NA100
A12: 1279989 | B12: Noah NA120 WT | C12: NOAH/NA120 | D12: Noah-NA | E12: ELActuator | F12: Item | G12: Rotork Price List Items | I12: Noah-NA | J12: NA120
A13: 1279993 | B13: Noah NA150 WT | C13: NOAH/NA150 | D13: Noah-NA | E13: ELActuator | F13: Item | G13: Rotork Price List Items | I13: Noah-NA | J13: NA150
... A37: 1280048 | B37: Noah SR50 WT | C37: NOAH/SR50 | D37: Noah-SR | E37: ELActuator | F37: Item | G37: Rotork Price List Items | I37: Noah-SR | J37: SR50

Sheet Industry code
A1: Category | B1: New Industry Code | C1: New AX/MTMS Description | D1: Old CE Code
A2: Oil & Gas | B2: 10 | C2: O&G - Upstream - Offshore | D2: A1, A2, A3, A4, A5
A3: Oil & Gas | B3: 11 | C3: O&G - Upstream - Onshore | D3: A6, A7, A8
A4: Oil & Gas | B4: 12 | C4: O&G - Upstream - Upstream carbon capture, utilisation & storage | D4: A9
A5: Oil & Gas | B5: 13 | C5: O&G - Midstream - Pipeline - liquids | D5: C2, C4, C5, C6, C7, C8
A6: Oil & Gas | B6: 14 | C6: O&G - Midstream - Pipeline - gas | D6: D2, D4, D5, D6, D8, D9
A7: Oil & Gas | B7: 15 | C7: O&G - Midstream - Terminals, storage & tank farms - liquid | D7: C3
A8: Oil & Gas | B8: 16 | C8: O&G - Midstream - Terminals, storage & tank farms - gas | D8: D3
A9: Oil & Gas | B9: 17 | C9: O&G - Midstream - LNG - liquefaction | D9: E2, E4
A10: Oil & Gas | B10: 18 | C10: O&G - Midstream - LNG - regasification | D10: E3, E5
A11: Oil & Gas | B11: 19 | C11: O&G - Midstream - LNG terminals & storage | D11: E1
A12: Oil & Gas | B12: 20 | C12: O&G - Midstream - Midstream carbon capture, utilisation & storage | D12: DA
A13: Oil & Gas | B13: 21 | C13: O&G - Downstream - Refining | D13: B1, B2, B3, B4, B5, B6
... A68: Chemical, Process & Industrial | B68: 93 | C68: CPI - Process - Pulp & paper and cement | D68: T3, T6
A69: Chemical, Process & Industrial | B69: 7G | C69: CPI - Process - HVAC Industrial | D69: Depreciated, 79
A70: Chemical, Process & Industrial | B70: G2 | C70: CPI - Industrial - GENERAL INDUSTRIAL USE | D70: Depreciated, 85
A71: Water & Power | B71: 4G | C71: W&P - Power - FOSSIL POWER - COAL | D71: Depreciated, 49

Sheet Customer master_국내
A1: 관리팀 Code | B1: 사업자번호 | C1: 거래처명 | D1: Customer Name ENG | E1: End country | F1: Currency | G1: Type | H1: OEM | I1: OEM 추가 설명 | J1: Reseller | K1: Reseller 추가 설명 | L1: Sector | M1: Sector 추가 설명 | N1: Payment Term | O1: Incoterms | P1: REMARK | Q1: RCK code mapping
A2: 005280 | B2: 261-85-00499 | C2: 주식회사티에스넥스젠 | D2: TS NEXGEN | E2: KOREA | F2: KRW | G2: TP | H2: N | J2: N | L2: CPI
A3: 007414 | B3: 119-81-42375 | C3: 욱삼건설주식회사 | D3: WOOKSAM CONSTRUCTION | E3: KOREA | F3: KRW | G3: TP | H3: N | J3: N | L3: WAPO
A4: 003547 | B4: 312-85-45076 | C4: (주) 센추리 아산공장 | D4: CENTURY | E4: KOREA | F4: KRW | G4: TP | H4: N | J4: N | L4: CPI
A5: 005091 | B5: 794-29-00426 | C5: 제이케이콘트롤 | D5: JK CONSTROLS | E5: KOREA | F5: KRW | G5: TP | H5: N | J5: Y | L5: CPI
A6: 004257 | B6: 306-82-00471 | C6: 한국수자원공사 | D6: K-WATER | E6: KOREA | F6: KRW | G6: TP | H6: N | J6: N | L6: WAPO
A7: 003467 | B7: 117-81-76942 | C7: 오토밸브엔지니어링 | D7: AUTO VALVE | E7: KOREA | F7: KRW | G7: TP | H7: N | J7: Y | L7: CPI
A8: 007705 | B8: 215-81-44948 | C8: 유텍종합건설(주) | D8: YUTEK TOTAL CONSTRUCTION | E8: KOREA | F8: KRW | G8: TP | H8: N | J8: N | L8: WAPO
A9: 006794 | B9: 775-88-01381 | C9: 주식회사 브이티엘 | D9: VTL | E9: KOREA | F9: KRW | G9: TP | H9: N | J9: Y | L9: CPI
A10: 007498 | B10: 247-03-02821 | C10: 글로브이 | D10: GLOV | E10: KOREA | F10: KRW | G10: TP | H10: N | J10: N | L10: WAPO
A11: 002271 | B11: 113-15-83752 | C11: 굿이엔지 | D11: GOODENG | E11: KOREA | F11: KRW | G11: TP | H11: N | I11: 3% 정도는 명판없이 나감 | J11: Y | L11: OG
A12: 006381 | B12: 394-81-01785 | C12: 유나텍 주식회사 | D12: YUNA TECH | E12: KOREA | F12: KRW | G12: TP | H12: N | J12: N | L12: CPI | M12: 단발성 거래 CPI로 분류
A13: 007506 | B13: 674-87-02305 | C13: 테크노아이앤피주식회사 | D13: TECHNO INP | E13: KOREA | F13: KRW | G13: TP | H13: N | J13: N | L13: WAPO
A14: 004174 | B14: 130-86-94744 | C14: 지콘(주) | D14: Z CON | E14: KOREA | F14: KRW | G14: TP | H14: N | J14: Y | L14: OG
A15: 005399 | B15: 606-02-51145 | C15: 경진산업 | D15: KYUNGJIN INDUSTRY | E15: KOREA | F15: KRW | G15: TP | H15: N | J15: N | L15: WAPO
A16: 004563 | B16: 814-01-00158 | C16: 이안컨트롤즈 | D16: IAN CONTROLS | E16: KOREA | F16: KRW | G16: TP | H16: N | J16: Y | L16: OG
A17: 006972 | B17: 105-49-01055 | C17: 아크솔루션 | D17: ARK SOLUTION | E17: KOREA | F17: KRW | G17: TP | H17: N | J17: Y | L17: WAPO
A18: 001845 | B18: 139-81-10936 | C18: (주)현대밸브 | D18: HYUNDAI VALVE | E18: KOREA | F18: KRW | G18: TP | H18: N | J18: N | L18: WAPO
A19: 007438 | B19: 113-86-01707 | C19: 미래밸브콘트롤(주) | D19: MIRAE VALVE CONTROL | E19: KOREA | F19: KRW | G19: TP | H19: N | J19: N | L19: CPI
A20: 007445 | B20: 504-82-08024 | C20: 한국농어촌공사 경북지역본부 | D20: KOREA RURAL COMMUNITY COR (GYEONGBUK) | E20: KOREA | F20: KRW | G20: TP | H20: N | J20: N | L20: WAPO
A21: 002557 | B21: 113-86-05741 | C21: 케이에이아이텍(주) | D21: KAI TECH | E21: KOREA | F21: KRW | G21: TP | H21: N | J21: Y | L21: CPI
A22: 001032 | B22: 139-81-40027 | C22: 상미에어텍(주) | D22: SANGMI AIRTECH | E22: KOREA | F22: KRW | G22: TP | H22: N | J22: Y | L22: CPI
A23: 004322 | B23: 602-81-13237 | C23: (주)호페코리아 | D23: HOPPE KOREA | E23: KOREA | F23: KRW | G23: TP | H23: N | J23: Y | L23: CPI
A24: 002725 | B24: 131-85-33796 | C24: 삼원알텍2공장 | D24: SAMWON ALTECH (PLANT 2) | E24: KOREA | F24: KRW | G24: TP | H24: N | J24: N | L24: CPI | M24: 단발성 거래 CPI로 분류
A25: 007437 | B25: 113-86-17723 | C25: 주식회사 에스제이브이 | D25: SJV | E25: KOREA | F25: KRW | G25: TP | H25: N | J25: N | L25: WAPO
A26: 002430 | B26: 606-81-95134 | C26: (주)티엠아이 | D26: TMI | E26: KOREA | F26: KRW | G26: TP | H26: Partial | I26: 5% 정도는 OEM(자체 명판으로 요청) | J26: Y | L26: OG
A27: 004955 | B27: 605-38-89706 | C27: 동광브이엔티(V&T) | D27: DONGKWANG V&T | E27: KOREA | F27: KRW | G27: TP | H27: N | J27: Y | L27: CPI
A28: 007391 | B28: 669-87-02230 | C28: 자이씨앤에이㈜ | D28: XI C&A | E28: KOREA | F28: KRW | G28: TP | H28: N | J28: N | L28: WAPO
A29: 006047 | B29: 609-81-04684 | C29: 두산에너빌리티(주) | D29: DOOSAN ENERBILITY | E29: KOREA | F29: KRW | G29: TP | H29: N | J29: N | L29: WAPO
A30: 006370 | B30: 134-85-55479 | C30: 영풍정밀(주)밸브공장 | D30: YOUNGPOONG PRECISION | E30: KOREA | F30: KRW | G30: TP | H30: N | J30: N | L30: CPI
A31: 004048 | B31: 603-81-10081 | C31: 하이에어코리아(주) | D31: HI-AIR KOREA | E31: KOREA | F31: KRW | G31: TP | H31: N | J31: N | L31: CPI
A32: 004723 | B32: 622-81-02020 | C32: (주)비와이 | D32: BY | E32: KOREA | F32: KRW | G32: TP | H32: N | J32: Y | L32: CPI
A33: 000736 | B33: 417-81-12417 | C33: (주)에스피씨 | D33: SPC | E33: KOREA | F33: KRW | G33: TP | H33: N | J33: N | L33: WAPO
A34: 007440 | B34: 423-86-00018 | C34: 주식회사 대상엔지니어링 | D34: DAESANG ENG | E34: KOREA | F34: KRW | G34: TP | H34: N | J34: N | L34: WAPO
A35: 005398 | B35: 387-63-00159 | C35: 고성테크 | D35: KOSUNG TECH | E35: KOREA | F35: KRW | G35: TP | H35: N | J35: Y | L35: CPI
A36: 005967 | B36: 632-81-00126 | C36: (주)휴텍 | D36: HUE TECH | E36: KOREA | F36: KRW | G36: TP | H36: N | J36: N | L36: CPI
A37: 001112 | B37: 113-81-65249 | C37: (주)대정밸브(서울) | D37: DAEJUNG VALVE-SEOUL | E37: KOREA | F37: KRW | G37: TP | H37: N | J37: Y | L37: CPI
A38: 003115 | B38: 503-81-86321 | C38: (주)포엠엔지니어링 | D38: 4M ENG | E38: KOREA | F38: KRW | G38: TP | H38: N | J38: Y | L38: OG
... A69: 007553 | B69: 206-86-06585 | C69: 주식회사 상지일렉스 | D69: SANGJI ELECS | E69: KOREA | F69: KRW | G69: TP | H69: N | J69: N | L69: CPI
A70: 006567 | B70: 517-10-01904 | C70: 대신ENG | D70: DAESHIN ENG | E70: KOREA | F70: KRW | G70: TP | H70: N | J70: Y | L70: CPI | M70: 단발성 거래 CPI로 분류
A71: 002295 | B71: 123-81-37492 | C71: (주)동양공조 | D71: DONGYANG AIR CONDITIONING | E71: KOREA | F71: KRW | G71: TP | H71: N | J71: N | L71: CPI
A72: 006138 | B72: 131-82-12320 | C72: 인천환경공단 승기사업소 | D72: INCHEON ENVIRONMENTAL CORPORATION (SENGGI) | E72: KOREA | F72: KRW | G72: TP | H72: N | J72: N | L72: WAPO
A73: 007634 | B73: 220-81-14937 | C73: 한국공장(주) | D73: KOREA FACTORY | E73: KOREA | F73: KRW | G73: TP | H73: N | J73: N | L73: CPI | P73: 영문명 없는 관계로 직역
A74: 007415 | B74: 634-86-00656 | C74: 주식회사 비전제어시스템 | D74: VISION CONTROL SYSTEM | E74: KOREA | F74: KRW | G74: TP | H74: N | J74: N | L74: CPI
A75: 003033 | B75: 604-81-08536 | C75: (주)보성엔지니어링 | D75: BOSUNG ENG | E75: KOREA | F75: KRW | G75: TP | H75: N | J75: N | L75: CPI
A76: 007711 | B76: 204-81-43105 | C76: (주)대청시스템스 | D76: DAECHUNG SYSTEMS | E76: KOREA | F76: KRW | G76: TP | H76: N | J76: N | L76: CPI
A77: 007192 | B77: 603-25-95949 | C77: 동아정밀공업사 | D77: DONGA PRECISION ENG | E77: KOREA | F77: KRW | G77: TP | H77: N | J77: N | L77: WAPO
A78: 004557 | B78: 121-23-36745 | C78: 태경 | D78: TAEKYEONG | E78: KOREA | F78: KRW | G78: TP | H78: N | J78: N | L78: CPI
A79: 006982 | B79: 678-37-00167 | C79: 씨앤케이엔지니어링(C&K ENG) | D79: C&K ENG | E79: KOREA | F79: KRW | G79: TP | H79: N | J79: Y | L79: CPI
A80: 004991 | B80: 612-85-00343 | C80: 삼성중공업(주)거제조선소 | D80: SAMSUNG HEAVY INDUSTRIES | E80: KOREA | F80: KRW | G80: TP | H80: N | J80: N | L80: CPI | M80: 단발성 거래 CPI로 분류
A81: 005936 | B81: 852-86-01272 | C81: ㈜서브원 | D81: SUBONE | E81: KOREA | F81: KRW | G81: TP | H81: N | J81: N | L81: CPI
A82: 005627 | B82: 610-85-21245 | C82: 한국동서발전(주)울산화력본부 | D82: KOREA EAST-WEST POWER (ULSAN) | E82: KOREA | F82: KRW | G82: TP | H82: N | J82: N | L82: WAPO
A83: 005455 | B83: 140-81-65974 | C83: (주)에스제이씨 | D83: SJC | E83: KOREA | F83: KRW | G83: TP | H83: N | J83: N | L83: CPI
A84: 006304 | B84: 305-81-52625 | C84: (주)영인 | D84: YEOUNGIN | E84: KOREA | F84: KRW | G84: TP | H84: N | J84: N | L84: CPI
A85: 002842 | B85: 108-81-43409 | C85: (주)대한송유관공사 | D85: DOPCO | E85: KOREA | F85: KRW | G85: TP | H85: N | J85: N | L85: WAPO
A86: 007614 | B86: 126-83-20015 | C86: 서울특별시 상수도사업본부 광암아리수정수센터 | D86: SEOUL WATER | E86: KOREA | F86: KRW | G86: TP | H86: N | J86: N | L86: WAPO
A87: 002196 | B87: 105-86-55444 | C87: (주)대도엔텍 | D87: DAEDO ENTEC | E87: KOREA | F87: KRW | G87: TP | H87: N | J87: Y | L87: CPI
A88: 006851 | B88: 139-82-02409 | C88: 인천교통공사 | D88: INCHEON TRANSIT CORPORATION | E88: KOREA | F88: KRW | G88: TP | H88: N | J88: N | L88: CPI
A89: 004697 | B89: 525-04-00278 | C89: 현승기공 | D89: HYUNSEUNG MECHNICAL IND | E89: KOREA | F89: KRW | G89: TP | H89: N | J89: N | L89: WAPO
A90: 007332 | B90: 615-81-88675 | C90: 엔이에스 주식회사 | D90: NES | E90: KOREA | F90: KRW | G90: TP | H90: N | J90: N | L90: CPI
A91: 007223 | B91: 606-81-10061 | C91: 유한회사 프라이그파이스트 | D91: PLEIGER FAR EAST | E91: KOREA | F91: KRW | G91: TP | H91: N | J91: N | L91: CPI
A92: 001989 | B92: 139-81-28455 | C92: 신라파이어(주) | D92: SINLA FIRE | E92: KOREA | F92: KRW | G92: TP | H92: N | J92: Y | L92: CPI
... A96: 007505 | B96: 689-34-00924 | C96: 리미트 | D96: LIMIT | E96: KOREA | F96: KRW | G96: TP | H96: N | J96: Y | L96: WAPO
A97: 007338 | B97: 174-11-00442 | C97: 스마트라인(Smart Line) | D97: SMART LINE | E97: KOREA | F97: KRW | G97: TP | H97: N | I97: 50% 정도는 OEM(자체 명판으로 요청) | J97: N | L97: CPI
A98: 005831 | B98: 582-81-01378 | C98: (주)밸만 | D98: BELMAN | E98: KOREA | F98: KRW | G98: TP | H98: N | J98: N | L98: CPI
A99: 007416 | B99: 407-83-01106 | C99: 남원시청 | D99: NAMWON-SI | E99: KOREA | F99: KRW | G99: TP | H99: N | J99: N | L99: WAPO
A100: 007654 | B100: 143-82-00486 | C100: (사)한국장애인협회 생산시설 | D100: KOREA ASSCOCIATION OF DISABLED PERSONS | E100: KOREA | F100: KRW | G100: TP | H100: N | J100: N | L100: CPI
A101: 006625 | B101: 636-19-00117 | C101: 바라테크 | D101: BARA TECH | E101: KOREA | F101: KRW | G101: TP | H101: N | J101: N | L101: CPI
A102: 005771 | B102: 677-86-01176 | C102: (주)에코비트워터 | D102: ECOBEAT WATER | E102: KOREA | F102: KRW | G102: TP | H102: N | J102: N | L102: WAPO
A103: 007707 | B103: 129-81-80022 | C103: 창현건업(주) | D103: CHANGHYEON CONSTRUCTION | E103: KOREA | F103: KRW | G103: TP | H103: N | J103: N | L103: CPI
A104: 003577 | B104: 220-88-22741 | C104: (주)이젠엔지니어링 | D104: IZEN ENG | E104: KOREA | F104: KRW | G104: TP | H104: N | J104: N | L104: CPI
A105: 006410 | B105: 131-83-00350 | C105: 인천광역시상수도사업본부수도시설관리소 | D105: INCHEON WATER TREATMENT CORPORATION (FACILITY MANAGEMENT) | E105: KOREA | F105: KRW | G105: TP | H105: N | J105: N | L105: WAPO
A106: 003711 | B106: 514-81-36568 | C106: (주)신정기공 | D106: SHINSUNG MECHNICAL IND | E106: KOREA | F106: KRW | G106: TP | H106: N | J106: N | L106: WAPO
A107: 007426 | B107: 412-81-19448 | C107: 주식회사 대유 | D107: DAEYU | E107: KOREA | F107: KRW | G107: TP | H107: N | J107: N | L107: WAPO
A108: 000613 | B108: 113-81-18616 | C108: 한국본산(주) | D108: KOMOTO | E108: KOREA | F108: KRW | G108: TP | H108: N | J108: N | L108: CPI
A109: 007427 | B109: 514-04-88181 | C109: SK산업 | D109: SK INDUSTRY | E109: KOREA | F109: KRW | G109: TP | H109: N | J109: N | L109: CPI
... A119: 005769 | B119: 312-81-40205 | C119: 광희엔지니어링(주) | D119: GWANGHEE ENG | E119: KOREA | F119: KRW | G119: TP | H119: N | J119: N | L119: WAPO
A120: 007250 | B120: 417-10-94855 | C120: 조이밸브 | D120: JOY VALVE | E120: KOREA | F120: KRW | G120: TP | H120: N | J120: Y | L120: CPI | P120: 영문명 없는 관계로 직역
A121: 007629 | B121: 435-81-02182 | C121: 주식회사 승원 | D121: SEUNGWON | E121: KOREA | F121: KRW | G121: TP | H121: N | J121: N | L121: CPI
A122: 005410 | B122: 131-86-35729 | C122: 디엠엔텍(주) | D122: DMNT | E122: KOREA | F122: KRW | G122: TP | H122: N | J122: N | L122: CPI | M122: 단발성 거래 CPI로 분류
A123: 007671 | B123: 129-86-50386 | C123: 이넵스주식회사 | D123: ENAPS | E123: KOREA | F123: KRW | G123: TP | H123: N | J123: N | L123: CPI | M123: 단발성 거래 CPI로 분류
A124: 006471 | B124: 223-83-03578 | C124: 강원도 홍천군 상하수도사업소 | D124: GANGWON WATER TREATMENT CORPORATION (HONGCHEON) | E124: KOREA | F124: KRW | G124: TP | H124: N | J124: N | L124: WAPO
A125: 007215 | B125: 604-81-07065 | C125: (주)딘텍 | D125: DINTEC | E125: KOREA | F125: KRW | G125: TP | H125: N | J125: N | L125: CPI
A126: 007319 | B126: 259-09-01356 | C126: 에스솔루션 | D126: S-SOLUTION | E126: KOREA | F126: KRW | G126: TP | H126: N | J126: N | L126: CPI
A127: 006848 | B127: 417-81-41474 | C127: 주식회사 엔티오스 | D127: NTOS CORPORATION | E127: KOREA | F127: KRW | G127: TP | H127: N | J127: N | L127: CPI | M127: 단발성 거래 CPI로 분류
A128: 007331 | B128: 587-88-00688 | C128: 주식회사 하이드로피아 | D128: HYDROPIA | E128: KOREA | F128: KRW | G128: TP | H128: N | J128: N | L128: CPI | M128: 단발성 거래 CPI로 분류
A129: 007631 | B129: 419-87-02367 | C129: 와이엠텍(주) | D129: YM TECH | E129: KOREA | F129: KRW | G129: TP | H129: N | J129: N | L129: CPI | M129: 단발성 거래 CPI로 분류
A130: 007596 | B130: 179-86-03419 | C130: 주식회사 에스솔루션 | D130: S-SOLUTION Co.,Ltd. | E130: KOREA | F130: KRW | G130: TP | H130: N | J130: N | L130: CPI | M130: 단발성 거래 CPI로 분류 | P130: 에스솔루션 아래와 같이 상호명 2개지만, 다른 회사입니다 에스솔루션 : S-SOLUTION ㈜에스솔루션 : S-SOLUTION Co.,LTD
A131: 004932 | B131: 130-83-00018 | C131: 부천시청 | D131: BUCHEON-SI | E131: KOREA | F131: KRW | G131: TP | H131: N | J131: N | L131: CPI | M131: 단발성 거래 CPI로 분류
A132: 005636 | B132: 137-82-05735 | C132: 인천환경공단 공촌사업소 | D132: INCHEON ENVIRONMENTAL CORPROATION (GONGCHON) | E132: KOREA | F132: KRW | G132: TP | H132: N | J132: N | L132: WAPO
A133: 007556 | B133: 201-81-96942 | C133: 이십일세기이엔지 주식회사 | D133: 21C ENG | E133: KOREA | F133: KRW | G133: TP | H133: N | J133: N | L133: CPI | M133: 단발성 거래 CPI로 분류
A134: 007441 | B134: 113-86-14314 | C134: 주식회사 삼성컨트롤밸브 | D134: SAMSUNG CONTROL VAVLE | E134: KOREA | F134: KRW | G134: TP | H134: N | J134: N | L134: CPI | M134: 단발성 거래 CPI로 분류
A135: 007425 | B135: 124-83-05041 | C135: 경기도 수원시 상수도사업소 | D135: GYEONGGI WATER TREATMENT CORPORATION (SUWON) | E135: KOREA | F135: KRW | G135: TP | H135: N | J135: N | L135: CPI | M135: 단발성 거래 CPI로 분류
A136: 004731 | B136: 603-81-26472 | C136: (주)동아산기 | D136: DONGA SANGI | E136: KOREA | F136: KRW | G136: TP | H136: N | J136: N | L136: CPI | M136: 단발성 거래 CPI로 분류
A137: 004643 | B137: 118-81-15012 | C137: 롯데케미칼(주) | D137: LOTTE CHEMICAL | E137: KOREA | F137: KRW | G137: TP | H137: N | J137: N | L137: CPI
A138: 007530 | B138: 339-82-00471 | C138: 사단법인 한국참여자치장애인총연합회 환경기계사업단 | D138: KOREA PARTICIPATORY‑AUTONOMY DISABLED PERSONS FEDERATION, ENVIRONMENT & MACHINERY PROJECT DIVISION | E138: KOREA | F138: KRW | G138: TP | H138: N | J138: N | L138: CPI | M138: 단발성 거래 CPI로 분류
A139: 006469 | B139: 137-82-05375 | C139: 인천환경공단강화사업소 | D139: INCHEON ENVIRONMENTAL CORORATION (GANGHWA) | E139: KOREA | F139: KRW | G139: TP | H139: N | J139: N | L139: WAPO
A140: 003924 | B140: 137-86-35412 | C140: 세진공조기계(주) | D140: SEJIN AMC | E140: KOREA | F140: KRW | G140: TP | H140: N | J140: N | L140: CPI
A141: 007239 | B141: 603-81-29289 | C141: 주식회사 파나시아 | D141: PANASIA | E141: KOREA | F141: KRW | G141: TP | H141: N | J141: N | L141: CPI
A142: 007500 | B142: 731-55-00424 | C142: 디엘시스템 | D142: DL SYSTEM | E142: KOREA | F142: KRW | G142: TP | H142: N | J142: N | L142: CPI | M142: 단발성 거래 CPI로 분류
...

Sheet Customer master_해외
A1: C-code by 해외 | B1: 고객명 | C1: 고객코드 | D1: Country | E1: Currency | F1: Type(TP/IC) | G1: OEM(Y/N) | H1: Reseller(Y/N) | I1: INCOTERMS | J1: Sector | K1: 비고 | M1: Payment Terms
A2: C-0095 | B2: WATERGATES GMBH | C2: 002352 | D2: GERMANY | E2: EUR | F2: T P | G2: Y | H2: Y | J2: CPI | K2: WATERGATES | M2: 60일
A3: C-0070 | B3: ROTORK CONTROL INC | C3: 002821 | D3: USA | E3: USD | F3: IC | G3: IC | H3: IC | J3: IC | K3: ROTORK CONTROLS MILWAUKEE | M3: 60일
A4: C-0076 | B4: ROTORK SWEDEN AB | C4: 003012 | D4: SWEDEN | E4: SEK | F4: IC | G4: IC | H4: IC | J4: IC | K4: RSA | M4: 60일
A5: C-0079 | B5: SECTORIEL SA | C5: 001883 | D5: FRANCE | E5: EUR | F5: T P | G5: Y | H5: Y | J5: CPI | K5: SECTORIEL | M5: 60일
A6: C-0075 | B6: ROTORK CONTROLS SINGAPORE | C6: 002576 | D6: SINGAPORE | E6: USD | F6: IC | G6: IC | H6: IC | J6: IC | K6: ROTORK SG | M6: 30일
A7: C-0065 | B7: PROVAL | C7: 002094 | D7: S. AFRICA | E7: USD | F7: T P | G7: N | H7: Y | J7: CPI | K7: PROVAL ACTUATION SA(PTY) LTD | M7: 30일
A8: C-0010 | B8: SHANDONG COPES | C8: 005378 | D8: CHINA | E8: USD | F8: T P | G8: N | H8: Y | J8: CPI | K8: Shandong COPES Automation Equipment Co., Ltd. | M8: 선불
A9: C-0066 | B9: PVD PRESES | C9: 001382 | D9: TURKEY | E9: USD | F9: T P | G9: N | H9: Y | J9: CPI | K9: PVD Proses Vana Donanim San. Ve Tic. Ltd. Sti. | M9: 30일
A10: C-0049 | B10: MESON AB | C10: 004321 | D10: SWEDEN | E10: EUR | F10: T P | G10: Y | H10: Y | J10: CPI | M10: 30일
A11: C-0054 | B11: MRC TRANSMARK PTE LTD | C11: 004678 | D11: New Zealand | E11: USD | F11: T P | G11: Y | H11: Y | J11: CPI | K11: MRC Global(New Zealand) Ltd. | M11: 60일
A12: C-0094 | B12: W&O EUROPE | C12: 004065 | D12: NETHERLAND | E12: EUR | F12: T P | G12: N | H12: Y | J12: CPI | M12: 선불
A13: C-0003 | B13: ACRODYNE | C13: 001095 | D13: AUSTRALIA | E13: USD | F13: T P | G13: Y | H13: Y | J13: WAPO | M13: 30일
A14: C-0035 | B14: FRESEVALVES | C14: 006282 | D14: DENMARK | E14: USD | F14: T P | G14: Y | H14: Y | J14: CPI | K14: FRESE DK | M14: 60일
A15: C-0048 | B15: NANJING KUNHUI FLUID EQUIPMENT | C15: 005842 | D15: CHINA | E15: USD | F15: T P | G15: N | H15: Y | J15: CPI | M15: 선불
A16: C-0062 | B16: OKM | C16: 001097 | D16: MALAYSIA | E16: USD | F16: T P | G16: N | H16: Y | J16: CPI | K16: OKM VALVE(M) SDN BHD | M16: 30일
B17: ASENI LLC | C17: 008068 | D17: UAE | E17: USD | F17: T P | G17: N | H17: Y | J17: CPI
A18: C-0042 | B18: THE JARDINE ENGINEERING | C18: 003109 | D18: HONG KONG | E18: USD | F18: T P | G18: N | H18: Y | J18: CPI | M18: 30일
A19: C-0028 | B19: FAGERBERG NORGE AS | C19: 004318 | D19: NORWAY | E19: EUR | F19: T P | G19: N | H19: Y | J19: WAPO | K19: FAGERBERG AS | M19: 30일
A20: C-0006 | B20: AN THINH PHAT INDUSTRIAL | C20: 006452 | D20: VIETNAM | E20: USD | F20: T P | G20: N | H20: Y | J20: CPI | M20: 선불
A21: C-0004 | B21: ADVANCED COMPONENT TECHNOL | C21: 002613 | D21: U.K. | E21: GBP | F21: T P | G21: N | H21: Y | J21: CPI | M21: 60일
A22: C-0077 | B22: RUNFLOW INDUSTRY | C22: 003446 | D22: CHINA | E22: USD | F22: T P | G22: N | H22: Y | J22: CPI | K22: SHANGHAI RUNFLOW CONTROLS CO., LTD | M22: 선불
A23: C-0091 | B23: CV URIPINDO DIGDAYA AGUNG | C23: 005902 | D23: INDONESIA | E23: USD | F23: T P | G23: N | H23: Y | J23: CPI | K23: URIPINDO | M23: 선불
A24: C-0008 | B24: BROEN SPOLKA Z OGRANICZONA | C24: 003449 | D24: POLAND | E24: EUR | F24: T P | G24: N | H24: Y | J24: WAPO | K24: BROEN | M24: 60일
A25: C-0059 | B25: NORDIC FLOW CONTROL PL | C25: 004455 | D25: SINGAPORE | E25: USD | F25: T P | G25: Y | H25: Y | J25: CPI | M25: 60일
A26: C-0108 | B26: DL TECH PTE LTD | C26: 005980 | D26: SINGAPORE | E26: USD | F26: T P | G26: N | H26: Y | J26: WAPO | M26: 선불
A27: C-0093 | B27: VALVECO LOGISTICS&SERVICES BV | C27: 007480 | D27: NETHERLAND | E27: EUR | F27: T P | G27: N | H27: Y | J27: CPI | M27: 60일
A28: C-0034 | B28: FLOMATIC CORPORATION | C28: 003729 | D28: USA | E28: USD | F28: T P | G28: Y | H28: Y | J28: WAPO | K28: FLOMATIC CORPORATION | M28: 60일
A29: C-0007 | B29: AXFLOW LIMITED | C29: 004151 | D29: IRELAND | E29: EUR | F29: T P | G29: N | H29: Y | J29: CPI | M29: 60일
A30: C-0061 | B30: CHANGSHA OUKE CONTROL VALVE | C30: 002238 | D30: CHINA | E30: USD | F30: T P | G30: N | H30: Y | J30: CPI | M30: 선불
A31: C-0085 | B31: NANTONG OK CRAGON INTERNATIONA | C31: 008224 | D31: CHINA | E31: USD | F31: T P | G31: N | H31: Y | J31: CPI | K31: NANTONG OK DRAGON INTERNALTIONAL TRADE(TCV) | M31: 선불
A32: C-0080 | B32: SEVAL COMPANY LIMITED | C32: 007509 | D32: VIETNAM | E32: USD | F32: T P | G32: N | H32: Y | J32: CPI | M32: 선불
B33: WOG VALVE SHANGHAIL CO.,LTD | C33: 008456 | D33: CHINA | E33: USD | F33: T P | G33: N | H33: Y | J33: CPI
A34: C-0053 | B34: MRC TRANSMARK B V | C34: 003197 | D34: NETHERLAND | E34: EUR | F34: T P | G34: Y | H34: Y | J34: OG | K34: MRC Global(Netherland) BV(MRC NL) | M34: 60일
B35: WELLSRING IMPORT AND EXPORT CO | C35: 008376 | D35: CHINA | E35: USD | F35: T P | G35: N | H35: Y | J35: WAPO
B36: ZIGONG ZIGAO VALVE CO.,LTD | C36: 008355 | D36: CHINA | E36: USD | F36: T P | G36: N | H36: Y | J36: CPI
B37: HANSAHANDELSHAUS OU | C37: 008356 | D37: ESTONIA | E37: USD | F37: T P | G37: N | H37: Y | J37: CPI
A38: C-0069 | B38: RAPHAEL VALVES INDUSTRIES | C38: 004388 | D38: ISRAEL | E38: USD | F38: T P | G38: N | H38: Y | J38: CPI | M38: 30일
A39: C-0071 | B39: ROCONSULT TECH SRL | C39: 007679 | D39: ROMANIA | E39: EUR | F39: T P | G39: N | H39: Y | J39: CPI | M39: 선불
A40: C-0037 | B40: FRONTLINE ENGINEERING | C40: 008535 | D40: THAILAND | E40: USD | F40: T P | G40: N | H40: Y | J40: CPI | M40: 선불
A41: C-0005 | B41: AQSA ENGINEERING PRODUCTS | C41: 007392 | D41: UAE | E41: USD | F41: T P | G41: N | H41: Y | J41: CPI | M41: 선불
B42: FANGZHENG VALVE | C42: 008398 | D42: CHINA | E42: USD | F42: T P | G42: N | H42: Y | J42: CPI
A43: C-0047 | B43: KSB LIMITED | C43: 004408 | D43: HONG KONG | E43: USD | F43: T P | G43: Y | H43: Y | J43: CPI | M43: 30일
A44: C-0090 | B44: UNIVALS | C44: 005844 | D44: SINGAPORE | E44: USD | F44: T P | G44: N | H44: Y | J44: CPI | K44: UNIVALS PTE LTD | M44: 선불
A45: C-0064 | B45: OVS ENGINEERING PTE. LTD. | C45: 005020 | D45: SINGAPORE | E45: USD | F45: T P | G45: Y(Heaton만) | H45: Y | J45: OG | M45: 30일
A46: C-0052 | B46: MRC TRANSMARK FINLAND | C46: 003495 | D46: FINLAND | E46: EUR | F46: T P | G46: Y | H46: Y | J46: OG | K46: MRC FIN | M46: 60일
A47: C-0012 | B47: CUSTOM ACTUATION | C47: 008568 | D47: U.K. | E47: GBP | F47: T P | G47: N | H47: Y | J47: CPI | M47: 선불
A48: C-0081 | B48: SEVI | C48: 008381 | D48: BULGARIA | E48: USD | F48: T P | G48: N | H48: Y | J48: CPI | K48: SEVI 2000 Ltd | M48: 선불
B49: PIONEER PRO LLC | C49: 006174 | D49: SINGAPORE | E49: USD | F49: T P | G49: N | H49: Y | J49: CPI
A50: C-0073 | B50: ROTORK TRANDING SHANGHAI C | C50: 006524 | D50: CHINA | E50: USD | F50: IC | G50: IC | H50: IC | J50: IC | K50: ROTORK CN | M50: 30일
A51: C-0039 | B51: GHIBSON ITALIA S R L | C51: 003087 | D51: ITALY | E51: EUR | F51: T P | G51: N | H51: Y | J51: CPI | M51: 선불
A52: C-0089 | B52: TRESIMECH PRIVATE LIMITED | C52: 008349 | D52: INDIA | E52: USD | F52: T P | G52: N | H52: Y | J52: CPI | M52: 선불
B53: EXION VIETNAM COMPANY LTD | C53: 008169 | D53: VIETNAM | E53: USD | F53: T P | G53: N | H53: Y | J53: CPI
A54: C-0051 | B54: MIDMAC GENERAL TRADING LLC | C54: 006281 | D54: UAE | E54: USD | F54: T P | G54: N | H54: Y | J54: OG | M54: 선불
A55: C-0002 | B55: ACDRA VALVES SL | C55: 003377 | D55: SPAIN | E55: EUR | F55: T P | G55: N | H55: Y | J55: CPI | M55: 선불
A56: C-0045 | B56: KLINGER FINLAND | C56: 004326 | D56: FINLAND | E56: EUR | F56: T P | G56: N | H56: Y | J56: CPI | M56: 선불
A57: C-0082 | B57: SOLARMAT | C57: 007363 | D57: HUNGARY | E57: EUR | F57: T P | G57: N | H57: Y | J57: CPI | K57: SOLAMAT S.P. | M57: 선불
A58: C-0021 | B58: ECONOSTO OY | C58: 007402 | D58: FINLAND | E58: EUR | F58: T P | G58: N | H58: Y | J58: CPI | K58: ECONOSTO FIN | M58: 선불
A59: C-0025 | B59: ELECO SERVICES | C59: 007508 | D59: SINGAPORE | E59: USD | F59: T P | G59: N | H59: Y | J59: CPI | M59: 선불
B60: INT YACHT SERVICES B V | C60: 008413 | D60: NETHERLAND | E60: EUR | F60: T P | G60: N | H60: Y | J60: CPI
B61: CORE TS PARTNERS LLC | C61: 008347 | D61: MONGOLIA | E61: USD | F61: T P | G61: N | H61: Y | J61: CPI
A62: C-0078 | B62: SAI GON VALVE CO.,LTD | C62: 008429 | D62: VIETNAM | E62: USD | F62: T P | G62: N | H62: Y | J62: CPI | M62: 선
B63: OEM | C63: 002247 | D63: UAE | E63: USD | F63: T P | G63: N | H63: Y | J63: CPI
A64: C-0074 | B64: ROTORK HGKONG | C64: 006422 | D64: HONG KONG | E64: USD | F64: IC | G64: IC | H64: IC | J64: IC | K64: ROTORK(LIMITED) HONGKONG | M64: 30일
B65: AL ZAWRAE INDUSTRIAL COMPANY | C65: 008671 | D65: UAE | E65: USD | F65: T P | G65: N | H65: Y | J65: CPI
B66: AL FATTAN SHIP INDUSTRY SO.PRO | C66: 008574 | D66: UAE | E66: USD | F66: T P | G66: N | H66: Y | J66: CPI
A67: C-0098 | B67: Y.J.SYSTEMS LTD | C67: 001874 | D67: ISRAEL | E67: USD | F67: T P | G67: N | H67: Y | J67: CPI | M67: 선불
B68: VT GLOBAL MARINE ENG. | C68: 003838 | D68: SINGAPORE | E68: USD | F68: T P | G68: N | H68: Y | J68: CPI
B69: GOSHREE INTERNATIONAL COMPANY | C69: 008550 | D69: INDIA | E69: USD | F69: T P | G69: N | H69: Y | J69: CPI
B70: THUYLUC | C70: 008454 | D70: VIETNAM | E70: USD | F70: T P | G70: N | H70: Y | J70: CPI
A71: C-0046 | B71: KOPECS | C71: 007817 | D71: CHINA | E71: USD | F71: T P | G71: N | H71: Y | J71: CPI | K71: Zhangjiagang KOPECS Industry Equipment Co., Ltd. | M71: 선불
A72: C-0125 | B72: ALCOMET AD | C72: 006073 | D72: BULGARIA | E72: EUR | F72: T P | G72: N | H72: Y | J72: CPI | M72: 선불
B73: MG NESH ENTREPRISE | C73: 008704 | F73: T P | G73: N | H73: Y | J73: CPI
B74: SHIP PARTS COM HONGKONG LIMITE | C74: 008300 | D74: HONG KONG | E74: USD | F74: T P | G74: N | H74: Y | J74: CPI
B75: CMA D ARGOUDELIS CO S A | C75: 008596 | D75: GREECE | E75: EUR | F75: T P | G75: N | H75: Y | J75: CPI
B76: ELECSER LTDA | C76: 008526 | D76: CHILE | E76: USD | F76: T P | G76: N | H76: Y | J76: CPI
B77: SIN GUANG MARINE PTE LTD | C77: 008681 | D77: SINGAPORE | E77: USD | F77: T P | G77: N | H77: Y | J77: CPI
B78: RUHA INTERNATIONAL BV | C78: 008525 | D78: NETHERLAND | E78: EUR | F78: T P | G78: N | H78: Y | J78: CPI
B79: BEERENBERG(THAILAND) CO LTD | C79: 008395 | D79: THAILAND | E79: USD | F79: T P | G79: N | H79: Y | J79: CPI
A80: C-0067 | B80: QUKO INT`L | C80: 002111 | D80: HONG KONG | E80: USD | F80: T P | G80: N | H80: Y | J80: CPI | M80: 선불
B81: ORIGIN PIPE JOINT STOCK COMPAN | C81: 008430 | D81: VIETNAM | E81: USD | F81: T P | G81: N | H81: Y | J81: CPI
B82: CAPRA VALVE(SUZHOU) CO.,LTD | D82: CHINA | E82: USD | F82: T P | G82: N | H82: Y | J82: CPI
B83: Wouter Witzel EuroValve B.V. | C83: 008350 | D83: NETHERLAND | E83: EUR | F83: T P | G83: N | H83: Y | J83: CPI
A84: C-0057 | B84: NOAH VALVE ACTUATOR | C84: 003234 | D84: USA | E84: USD | F84: T P | G84: N | H84: Y | J84: CPI | K84: NOAH VALVE ACTUATION INC | M84: 60일
A85: C-0079 | B85: SECTORIEL | C85: 002499 | D85: FRANCE | E85: EUR | F85: T P | G85: Y | H85: Y | J85: CPI | L85: 중복line5 | M85: 60일
A86: C-0070 | B86: ROTORK CONTROLS.INC | C86: 002915 | D86: USA | E86: USD | F86: IC | G86: IC | H86: IC | J86: IC | K86: ROTORK CONTROLS MILWAUKEE | L86: 중복line3 | M86: 60일
B87: PETROLEUM OFFSHORE | C87: 006296 | D87: VIETNAM | E87: USD | F87: T P | G87: N | H87: Y | J87: OG
A88: C-0066 | B88: PVD PROSES | C88: 002279 | D88: TURKEY | E88: USD | F88: T P | G88: N | H88: Y | J88: CPI | L88: 중북line9 | M88: 30일
B89: VIEN DONG MARINE ANS PETRO; | C89: 007799 | D89: VIETNAM | E89: USD | F89: T P | G89: N | H89: Y | J89: CPI
B90: STAITS TOOLS SDN AHD | C90: 007946 | D90: MALAYSIA | E90: USD | F90: T P | G90: N | H90: Y | J90: CPI
A91: C-0085 | B91: NANTONG OK DRAGON INTERNATIONA | C91: 007742 | D91: CHINA | E91: USD | F91: T P | G91: N | H91: Y | J91: CPI | K91: NANTONG OK DRAGO INTERNATIONAL TRADE(TCV) | L91: 중복line31 | M91: 선불
A92: C-0093 | B92: VALVECO-LOGISTICS | C92: 005845 | D92: NETHERLAND | E92: EUR | F92: T P | G92: N | H92: Y | J92: CPI | L92: 중복line27 | M92: 60일
A93: C-0006 | B93: AN THINH PHAT INDUSTRIAL | C93: 005514 | D93: VIETNAM | E93: USD | F93: T P | G93: N | H93: Y | J93: CPI | L93: 중복line20 | M93: 선불
A94: C-0007 | B94: AXFLOW LIMI LTD | C94: 006426 | D94: IRELAND | E94: USD | F94: T P | G94: N | H94: Y | J94: CPI | L94: 중복line29 | M94: 60일
A95: C-0037 | B95: FRONTLINE NGINEERING | C95: 007576 | D95: THAILAND | E95: USD | F95: T P | G95: N | H95: Y | J95: CPI | L95: 중복line40 | M95: 선불
A96: C-0029 | B96: FASTLINE TECHINCAL SERVICES | C96: 004867 | D96: OMAN | E96: USD | F96: T P | G96: N | H96: Y | J96: CPI | M96: 선불
A97: C-0075 | B97: ROTORK CONTROLS SNGAPOR | C97: 003041 | D97: SINGAPORE | E97: USD | F97: IC | G97: IC | H97: IC | J97: IC | K97: ROTORK CONTROLS SINGAPORE(ROTORK SG) | L97: 중복line6 | M97: 30일
B98: NMP TRADING AND SERVICE ONE | C98: 007722 | D98: SINGAPORE | E98: USD | F98: T P | G98: N | H98: Y | J98: CPI
B99: GOH GENERAL ENGINEERING | C99: 008003 | D99: SINGAPORE | E99: USD | F99: T P | G99: N | H99: Y | J99: CPI
A100: C-0078 | B100: SAI GON VALVECO.,LTD | C100: 007941 | D100: VIETNAM | E100: USD | F100: T P | G100: N | H100: Y | J100: CPI | L100: 중복line62 | M100: 선불
...

Sheet ICO
A1: Model | B1: Option | C1: Price | D1: Remarks | E1: Key
A2: SA003 | B2: SA003 | C2: 143914.69 | E2: =A2&B2 -> SA003SA003
A3: SA003 | B3: Bush | C3: 0 | D3: FREE | E3: =A3&B3 -> SA003Bush
A4: SA003 | B4: Bush-SQ | C4: 0 | D4: N/A | E4: =A4&B4 -> SA003Bush-SQ
A5: SA003 | B5: Bush-STAR | C5: 0 | D5: N/A | E5: =A5&B5 -> SA003Bush-STAR
A6: SA003 | B6: ALS | C6: 0 | D6: FREE | E6: =A6&B6 -> SA003ALS
A7: SA003 | B7: ATS | C7: 0 | D7: N/A | E7: =A7&B7 -> SA003ATS
A8: SA003 | B8: EXT | C8: 71957.345 | E8: =A8&B8 -> SA003EXT
A9: SA003 | B9: LCU | C9: 0 | D9: N/A | E9: =A9&B9 -> SA003LCU
A10: SA003 | B10: INTEGRAL | C10: 0 | D10: N/A | E10: =A10&B10 -> SA003INTEGRAL
A11: SA003 | B11: PIU | C11: 0 | D11: N/A | E11: =A11&B11 -> SA003PIU
A12: SA003 | B12: CPT+PIU | C12: 0 | D12: N/A | E12: =A12&B12 -> SA003CPT+PIU
A13: SA003 | B13: PCU+PIU | C13: 0 | D13: N/A | E13: =A13&B13 -> SA003PCU+PIU
A14: SA003 | B14: IMS | C14: 0 | D14: N/A | E14: =A14&B14 -> SA003IMS
A15: SA003 | B15: DC24V | C15: 0 | D15: FREE | E15: =A15&B15 -> SA003DC24V
A16: SA003 | B16: BLDC | C16: 0 | D16: N/A | E16: =A16&B16 -> SA003BLDC
A17: SA003 | B17: -40 | C17: 0 | D17: N/A | E17: =A17&B17 -> SA003-40
A18: SA003 | B18: -60 | C18: 0 | D18: N/A | E18: =A18&B18 -> SA003-60
A19: SA003 | B19: EXP | C19: 0 | D19: N/A | E19: =A19&B19 -> SA003EXP
A20: SA003 | B20: SCP | C20: 0 | D20: N/A | E20: =A20&B20 -> SA003SCP
A21: SA003 | B21: Modbus, Profibus | C21: 791530.79 | E21: =A21&B21 -> SA003Modbus, Profibus
A22: SA003 | B22: HART, Foundation Fieldbus | C22: 0 | D22: N/A | E22: =A22&B22 -> SA003HART, Foundation Fieldbus
A23: SA005 | B23: SA005 | C23: 175575.92 | E23: =A23&B23 -> SA005SA005
A24: SA005 | B24: Bush | C24: 0 | D24: FREE | E24: =A24&B24 -> SA005Bush
A25: SA005 | B25: Bush-SQ | C25: 0 | D25: N/A | E25: =A25&B25 -> SA005Bush-SQ
A26: SA005 | B26: Bush-STAR | C26: 0 | D26: N/A | E26: =A26&B26 -> SA005Bush-STAR
A27: SA005 | B27: ALS | C27: 0 | D27: FREE | E27: =A27&B27 -> SA005ALS
A28: SA005 | B28: ATS | C28: 0 | D28: N/A | E28: =A28&B28 -> SA005ATS
A29: SA005 | B29: EXT | C29: 71957.345 | E29: =A29&B29 -> SA005EXT
A30: SA005 | B30: LCU | C30: 0 | D30: N/A | E30: =A30&B30 -> SA005LCU
A31: SA005 | B31: INTEGRAL | C31: 0 | D31: N/A | E31: =A31&B31 -> SA005INTEGRAL
A32: SA005 | B32: PIU | C32: 0 | D32: N/A | E32: =A32&B32 -> SA005PIU
A33: SA005 | B33: CPT+PIU | C33: 0 | D33: N/A | E33: =A33&B33 -> SA005CPT+PIU
A34: SA005 | B34: PCU+PIU | C34: 0 | D34: N/A | E34: =A34&B34 -> SA005PCU+PIU
A35: SA005 | B35: IMS | C35: 0 | D35: N/A | E35: =A35&B35 -> SA005IMS
A36: SA005 | B36: DC24V | C36: 0 | D36: FREE | E36: =A36&B36 -> SA005DC24V
A37: SA005 | B37: BLDC | C37: 0 | D37: N/A | E37: =A37&B37 -> SA005BLDC
A38: SA005 | B38: -40 | C38: 0 | D38: N/A | E38: =A38&B38 -> SA005-40
A39: SA005 | B39: -60 | C39: 0 | D39: N/A | E39: =A39&B39 -> SA005-60
A40: SA005 | B40: EXP | C40: 0 | D40: N/A | E40: =A40&B40 -> SA005EXP
A41: SA005 | B41: SCP | C41: 0 | D41: N/A | E41: =A41&B41 -> SA005SCP
A42: SA005 | B42: Modbus, Profibus | C42: 791530.79 | E42: =A42&B42 -> SA005Modbus, Profibus
A43: SA005 | B43: HART, Foundation Fieldbus | C43: 0 | D43: N/A | E43: =A43&B43 -> SA005HART, Foundation Fieldbus
A44: SA005L | B44: SA005L | C44: 182771.66 | E44: =A44&B44 -> SA005LSA005L
A45: SA005L | B45: Bush | C45: 0 | D45: FREE | E45: =A45&B45 -> SA005LBush
A46: SA005L | B46: Bush-SQ | C46: 0 | D46: N/A | E46: =A46&B46 -> SA005LBush-SQ
A47: SA005L | B47: Bush-STAR | C47: 0 | D47: N/A | E47: =A47&B47 -> SA005LBush-STAR
A48: SA005L | B48: ALS | C48: 0 | D48: FREE | E48: =A48&B48 -> SA005LALS
A49: SA005L | B49: ATS | C49: 0 | D49: N/A | E49: =A49&B49 -> SA005LATS
A50: SA005L | B50: EXT | C50: 71957.345 | E50: =A50&B50 -> SA005LEXT
A51: SA005L | B51: LCU | C51: 215872.04 | E51: =A51&B51 -> SA005LLCU
A52: SA005L | B52: INTEGRAL | C52: 0 | D52: N/A | E52: =A52&B52 -> SA005LINTEGRAL
A53: SA005L | B53: PIU | C53: 57565.876 | E53: =A53&B53 -> SA005LPIU
A54: SA005L | B54: CPT+PIU | C54: 129523.22 | E54: =A54&B54 -> SA005LCPT+PIU
A55: SA005L | B55: PCU+PIU | C55: 259046.44 | E55: =A55&B55 -> SA005LPCU+PIU
A56: SA005L | B56: IMS | C56: 0 | D56: N/A | E56: =A56&B56 -> SA005LIMS
A57: SA005L | B57: DC24V | C57: 0 | D57: FREE | E57: =A57&B57 -> SA005LDC24V
A58: SA005L | B58: BLDC | C58: 0 | D58: N/A | E58: =A58&B58 -> SA005LBLDC
A59: SA005L | B59: -40 | C59: 79153.079 | E59: =A59&B59 -> SA005L-40
A60: SA005L | B60: -60 | C60: 0 | D60: N/A | E60: =A60&B60 -> SA005L-60
A61: SA005L | B61: EXP | C61: 0 | D61: N/A | E61: =A61&B61 -> SA005LEXP
A62: SA005L | B62: SCP | C62: 503701.41 | E62: =A62&B62 -> SA005LSCP
A63: SA005L | B63: Modbus, Profibus | C63: 791530.79 | E63: =A63&B63 -> SA005LModbus, Profibus
A64: SA005L | B64: HART, Foundation Fieldbus | C64: 0 | D64: N/A | E64: =A64&B64 -> SA005LHART, Foundation Fieldbus
A65: SA005X | B65: SA005X | C65: 259046.44 | E65: =A65&B65 -> SA005XSA005X
A66: SA005X | B66: Bush | C66: 0 | D66: FREE | E66: =A66&B66 -> SA005XBush
A67: SA005X | B67: Bush-SQ | C67: 0 | D67: N/A | E67: =A67&B67 -> SA005XBush-SQ
A68: SA005X | B68: Bush-STAR | C68: 0 | D68: N/A | E68: =A68&B68 -> SA005XBush-STAR
A69: SA005X | B69: ALS | C69: 0 | D69: FREE | E69: =A69&B69 -> SA005XALS
A70: SA005X | B70: ATS | C70: 0 | D70: N/A | E70: =A70&B70 -> SA005XATS
A71: SA005X | B71: EXT | C71: 71957.345 | E71: =A71&B71 -> SA005XEXT
A72: SA005X | B72: LCU | C72: 0 | D72: N/A | E72: =A72&B72 -> SA005XLCU
A73: SA005X | B73: INTEGRAL | C73: 0 | D73: N/A | E73: =A73&B73 -> SA005XINTEGRAL
A74: SA005X | B74: PIU | C74: 57565.876 | E74: =A74&B74 -> SA005XPIU
A75: SA005X | B75: CPT+PIU | C75: 129523.22 | E75: =A75&B75 -> SA005XCPT+PIU
A76: SA005X | B76: PCU+PIU | C76: 259046.44 | E76: =A76&B76 -> SA005XPCU+PIU
A77: SA005X | B77: IMS | C77: 0 | D77: N/A | E77: =A77&B77 -> SA005XIMS
A78: SA005X | B78: DC24V | C78: 0 | D78: FREE | E78: =A78&B78 -> SA005XDC24V
A79: SA005X | B79: BLDC | C79: 0 | D79: N/A | E79: =A79&B79 -> SA005XBLDC
A80: SA005X | B80: -40 | C80: 79153.079 | E80: =A80&B80 -> SA005X-40
A81: SA005X | B81: -60 | C81: 0 | D81: N/A | E81: =A81&B81 -> SA005X-60
A82: SA005X | B82: EXP | C82: 0 | D82: EXP | E82: =A82&B82 -> SA005XEXP
A83: SA005X | B83: SCP | C83: 503701.41 | E83: =A83&B83 -> SA005XSCP
A84: SA005X | B84: Modbus, Profibus | C84: 791530.79 | E84: =A84&B84 -> SA005XModbus, Profibus
A85: SA005X | B85: HART, Foundation Fieldbus | C85: 0 | D85: N/A | E85: =A85&B85 -> SA005XHART, Foundation Fieldbus
A86: SA009S | B86: SA009S | C86: 212993.74 | E86: =A86&B86 -> SA009SSA009S
A87: SA009S | B87: Bush | C87: 0 | D87: FREE | E87: =A87&B87 -> SA009SBush
A88: SA009S | B88: Bush-SQ | C88: 0 | D88: N/A | E88: =A88&B88 -> SA009SBush-SQ
A89: SA009S | B89: Bush-STAR | C89: 0 | D89: N/A | E89: =A89&B89 -> SA009SBush-STAR
A90: SA009S | B90: ALS | C90: 0 | D90: FREE | E90: =A90&B90 -> SA009SALS
A91: SA009S | B91: ATS | C91: 0 | D91: N/A | E91: =A91&B91 -> SA009SATS
A92: SA009S | B92: EXT | C92: 71957.345 | E92: =A92&B92 -> SA009SEXT
A93: SA009S | B93: LCU | C93: 0 | D93: N/A | E93: =A93&B93 -> SA009SLCU
A94: SA009S | B94: INTEGRAL | C94: 0 | D94: N/A | E94: =A94&B94 -> SA009SINTEGRAL
A95: SA009S | B95: PIU | C95: 0 | D95: N/A | E95: =A95&B95 -> SA009SPIU
A96: SA009S | B96: CPT+PIU | C96: 0 | D96: N/A | E96: =A96&B96 -> SA009SCPT+PIU
A97: SA009S | B97: PCU+PIU | C97: 0 | D97: N/A | E97: =A97&B97 -> SA009SPCU+PIU
A98: SA009S | B98: IMS | C98: 0 | D98: N/A | E98: =A98&B98 -> SA009SIMS
A99: SA009S | B99: DC24V | C99: 0 | D99: FREE | E99: =A99&B99 -> SA009SDC24V
A100: SA009S | B100: BLDC | C100: 0 | D100: N/A | E100: =A100&B100 -> SA009SBLDC
...

Sheet Sheet1
B2: 제이케이콘트롤 | D2: CPI | F2: 1279970 | G2: NA038 | H2: KRW | I2: 1 | J2: 1288000 | K2: =표3[[#This Row],[Item qty]]*표3[[#This Row],[Sales Unit Price]] -> 19250000 | L2: {=_xlfn.XLOOKUP($BB2&$BB2,ICO!$E:$E,ICO!$C:$C,0)+SUMPRODUCT((AW2:BP2="Y")*_xlfn.XLOOKUP($BB2&AW$1:BP$1,ICO!$E:$E,ICO!$C:$C,0))} -> 0 | M2: =표3[[#This Row],[ICO Unit]]*표3[[#This Row],[Item qty]] -> 20294842 | N2: DDP | P2: 이용욱 | R2: 46030 | T2: 46050 | U2: TBD | X2: 220V-1Ph-60Hz | AF2: ◇17 | AG2: Y (BFV200A) 신우밸브 사급 | AL2: 내장 PCU | AN2: IP67 | AO2: PF 3/4" | AP2: M/S | AV2: NA038 | AW2: Y | AX2: Y | BE2: Y | BJ2: Y
B8: 제이케이콘트롤 | D8: CPI | F8: 1279970 | G8: NA038 with BFV | H8: KRW | I8: 22 | J8: 875000 | K8: =표3[[#This Row],[Item qty]]*표3[[#This Row],[Sales Unit Price]] -> 4050000 | L8: {=_xlfn.XLOOKUP($BB8&$BB8,ICO!$E:$E,ICO!$C:$C,0)+SUMPRODUCT((AW8:BP8="Y")*_xlfn.XLOOKUP($BB8&AW$1:BP$1,ICO!$E:$E,ICO!$C:$C,0))} -> 0 | M8: =표3[[#This Row],[ICO Unit]]*표3[[#This Row],[Item qty]] -> 0 | N8: DDP | P8: 이용욱 | T8: 46059
